{
  "1966": {
    "espn_name": "LeBron James",
    "rotowire_slug": "lebron-james-2344",
    "rotowire_id": "2344"
  },
  "2284101": {
    "espn_name": "Justin Holiday",
    "rotowire_slug": "justin-holiday-3242",
    "rotowire_id": "3242"
  },
  "2326307": {
    "espn_name": "Seth Curry",
    "rotowire_slug": "seth-curry-3498",
    "rotowire_id": "3498"
  },
  "2451037": {
    "espn_name": "Daniel Theis",
    "rotowire_slug": "daniel-theis-3523",
    "rotowire_id": "3523"
  },
  "2488653": {
    "espn_name": "Mason Plumlee",
    "rotowire_slug": "mason-plumlee-3442",
    "rotowire_id": "3442"
  },
  "2488945": {
    "espn_name": "Tim Frazier",
    "rotowire_slug": "tim-frazier-3695",
    "rotowire_id": "3695"
  },
  "2489663": {
    "espn_name": "Kelly Olynyk",
    "rotowire_slug": "kelly-olynyk-3443",
    "rotowire_id": "3443"
  },
  "2490149": {
    "espn_name": "CJ McCollum",
    "rotowire_slug": "cj-mccollum-3437",
    "rotowire_id": "3437"
  },
  "2527963": {
    "espn_name": "Victor Oladipo",
    "rotowire_slug": "victor-oladipo-3433",
    "rotowire_id": "3433"
  },
  "2528210": {
    "espn_name": "Tim Hardaway Jr.",
    "rotowire_slug": "tim-hardaway-3459",
    "rotowire_id": "3459"
  },
  "2528426": {
    "espn_name": "Jordan Clarkson",
    "rotowire_slug": "jordan-clarkson-3614",
    "rotowire_id": "3614"
  },
  "2528588": {
    "espn_name": "Doug McDermott",
    "rotowire_slug": "doug-mcdermott-3579",
    "rotowire_id": "3579"
  },
  "2528693": {
    "espn_name": "Torrey Craig",
    "rotowire_slug": "torrey-craig-4214",
    "rotowire_id": "4214"
  },
  "2530530": {
    "espn_name": "T.J. McConnell",
    "rotowire_slug": "tj-mcconnell-3760",
    "rotowire_id": "3760"
  },
  "2531367": {
    "espn_name": "Dwight Powell",
    "rotowire_slug": "dwight-powell-3610",
    "rotowire_id": "3610"
  },
  "2566769": {
    "espn_name": "Malcolm Brogdon",
    "rotowire_slug": "malcolm-brogdon-3898",
    "rotowire_id": "3898"
  },
  "2578185": {
    "espn_name": "Dorian Finney-Smith",
    "rotowire_slug": "dorian-finney-smith-3911",
    "rotowire_id": "3911"
  },
  "2578239": {
    "espn_name": "Pat Connaughton",
    "rotowire_slug": "pat-connaughton-3727",
    "rotowire_id": "3727"
  },
  "2579258": {
    "espn_name": "Cody Zeller",
    "rotowire_slug": "cody-zeller-3438",
    "rotowire_id": "3438"
  },
  "2579294": {
    "espn_name": "Frank Kaminsky",
    "rotowire_slug": "frank-kaminsky-3713",
    "rotowire_id": "3713"
  },
  "2580365": {
    "espn_name": "Larry Nance Jr.",
    "rotowire_slug": "larry-nance-3723",
    "rotowire_id": "3723"
  },
  "2580782": {
    "espn_name": "Spencer Dinwiddie",
    "rotowire_slug": "spencer-dinwiddie-3616",
    "rotowire_id": "3616"
  },
  "2581018": {
    "espn_name": "Kentavious Caldwell-Pope",
    "rotowire_slug": "kentavious-caldwell-pope-3450",
    "rotowire_id": "3450"
  },
  "2581184": {
    "espn_name": "Anthony Gill",
    "rotowire_slug": "anthony-gill-5309",
    "rotowire_id": "5309"
  },
  "2581190": {
    "espn_name": "Josh Richardson",
    "rotowire_slug": "josh-richardson-3770",
    "rotowire_id": "3770"
  },
  "2583632": {
    "espn_name": "Royce O'Neale",
    "rotowire_slug": "royce-oneale-3977",
    "rotowire_id": "3977"
  },
  "2583639": {
    "espn_name": "Elfrid Payton",
    "rotowire_slug": "elfrid-payton-3594",
    "rotowire_id": "3594"
  },
  "2595209": {
    "espn_name": "Damion Lee",
    "rotowire_slug": "damion-lee-3947",
    "rotowire_id": "3947"
  },
  "2595516": {
    "espn_name": "Norman Powell",
    "rotowire_slug": "norman-powell-3726",
    "rotowire_id": "3726"
  },
  "2596107": {
    "espn_name": "Alex Len",
    "rotowire_slug": "alex-len-3436",
    "rotowire_id": "3436"
  },
  "2596112": {
    "espn_name": "Javonte Green",
    "rotowire_slug": "javonte-green-4588",
    "rotowire_id": "4588"
  },
  "2779": {
    "espn_name": "Chris Paul",
    "rotowire_slug": "chris-paul-2584",
    "rotowire_id": "2584"
  },
  "2960236": {
    "espn_name": "Maxi Kleber",
    "rotowire_slug": "maxi-kleber-3658",
    "rotowire_id": "3658"
  },
  "2968436": {
    "espn_name": "Joe Ingles",
    "rotowire_slug": "joe-ingles-3689",
    "rotowire_id": "3689"
  },
  "2982334": {
    "espn_name": "T.J. Warren",
    "rotowire_slug": "tj-warren-3585",
    "rotowire_id": "3585"
  },
  "2990962": {
    "espn_name": "Taurean Prince",
    "rotowire_slug": "taurean-prince-3858",
    "rotowire_id": "3858"
  },
  "2990969": {
    "espn_name": "Georges Niang",
    "rotowire_slug": "georges-niang-3917",
    "rotowire_id": "3917"
  },
  "2990984": {
    "espn_name": "Buddy Hield",
    "rotowire_slug": "buddy-hield-3884",
    "rotowire_id": "3884"
  },
  "2990992": {
    "espn_name": "Marcus Smart",
    "rotowire_slug": "marcus-smart-3575",
    "rotowire_id": "3575"
  },
  "2991043": {
    "espn_name": "Caris LeVert",
    "rotowire_slug": "caris-levert-3914",
    "rotowire_id": "3914"
  },
  "2991070": {
    "espn_name": "Jerami Grant",
    "rotowire_slug": "jerami-grant-3588",
    "rotowire_id": "3588"
  },
  "2991139": {
    "espn_name": "Kris Dunn",
    "rotowire_slug": "kris-dunn-3854",
    "rotowire_id": "3854"
  },
  "2991230": {
    "espn_name": "Fred VanVleet",
    "rotowire_slug": "fred-vanvleet-3935",
    "rotowire_id": "3935"
  },
  "2991235": {
    "espn_name": "Steven Adams",
    "rotowire_slug": "steven-adams-3445",
    "rotowire_id": "3445"
  },
  "2991350": {
    "espn_name": "Alex Caruso",
    "rotowire_slug": "alex-caruso-3952",
    "rotowire_id": "3952"
  },
  "2993370": {
    "espn_name": "Richaun Holmes",
    "rotowire_slug": "richaun-holmes-3755",
    "rotowire_id": "3755"
  },
  "2993874": {
    "espn_name": "Kyle Anderson",
    "rotowire_slug": "kyle-anderson-3586",
    "rotowire_id": "3586"
  },
  "2999547": {
    "espn_name": "Gary Harris",
    "rotowire_slug": "gary-harris-3582",
    "rotowire_id": "3582"
  },
  "3012": {
    "espn_name": "Kyle Lowry",
    "rotowire_slug": "kyle-lowry-2720",
    "rotowire_id": "2720"
  },
  "3032976": {
    "espn_name": "Rudy Gobert",
    "rotowire_slug": "rudy-gobert-3440",
    "rotowire_id": "3440"
  },
  "3032977": {
    "espn_name": "Giannis Antetokounmpo",
    "rotowire_slug": "giannis-antetokounmpo-3456",
    "rotowire_id": "3456"
  },
  "3032978": {
    "espn_name": "Dario Saric",
    "rotowire_slug": "dario-saric-3451",
    "rotowire_id": "3451"
  },
  "3032979": {
    "espn_name": "Dennis Schroder",
    "rotowire_slug": "dennis-schroder-3444",
    "rotowire_id": "3444"
  },
  "3033": {
    "espn_name": "P.J. Tucker",
    "rotowire_slug": "pj-tucker-2708",
    "rotowire_id": "2708"
  },
  "3037789": {
    "espn_name": "Bogdan Bogdanovic",
    "rotowire_slug": "bogdan-bogdanovic-3593",
    "rotowire_id": "3593"
  },
  "3056245": {
    "espn_name": "Malcolm Hill",
    "rotowire_slug": "malcolm-hill-4150",
    "rotowire_id": "4150"
  },
  "3058254": {
    "espn_name": "Christian Wood",
    "rotowire_slug": "christian-wood-3778",
    "rotowire_id": "3778"
  },
  "3059310": {
    "espn_name": "Monte Morris",
    "rotowire_slug": "monte-morris-4135",
    "rotowire_id": "4135"
  },
  "3059318": {
    "espn_name": "Joel Embiid",
    "rotowire_slug": "joel-embiid-3572",
    "rotowire_id": "3572"
  },
  "3059319": {
    "espn_name": "Andrew Wiggins",
    "rotowire_slug": "andrew-wiggins-3571",
    "rotowire_id": "3571"
  },
  "3059358": {
    "espn_name": "Deonte Burton",
    "rotowire_slug": "deonte-burton-4633",
    "rotowire_id": "4633"
  },
  "3059409": {
    "espn_name": "Nigel Hayes-Davis",
    "rotowire_slug": "nigel-hayes-davis-4149",
    "rotowire_id": "4149"
  },
  "3062679": {
    "espn_name": "Josh Hart",
    "rotowire_slug": "josh-hart-4136",
    "rotowire_id": "4136"
  },
  "3064230": {
    "espn_name": "Cameron Payne",
    "rotowire_slug": "cameron-payne-3744",
    "rotowire_id": "3744"
  },
  "3064290": {
    "espn_name": "Aaron Gordon",
    "rotowire_slug": "aaron-gordon-3577",
    "rotowire_id": "3577"
  },
  "3064320": {
    "espn_name": "George King",
    "rotowire_slug": "george-king-4469",
    "rotowire_id": "4469"
  },
  "3064440": {
    "espn_name": "Zach LaVine",
    "rotowire_slug": "zach-lavine-3597",
    "rotowire_id": "3597"
  },
  "3064447": {
    "espn_name": "Delon Wright",
    "rotowire_slug": "delon-wright-3710",
    "rotowire_id": "3710"
  },
  "3064482": {
    "espn_name": "Bobby Portis",
    "rotowire_slug": "bobby-portis-3705",
    "rotowire_id": "3705"
  },
  "3064514": {
    "espn_name": "Julius Randle",
    "rotowire_slug": "julius-randle-3574",
    "rotowire_id": "3574"
  },
  "3064560": {
    "espn_name": "Luke Kornet",
    "rotowire_slug": "luke-kornet-4151",
    "rotowire_id": "4151"
  },
  "3074752": {
    "espn_name": "Terry Rozier",
    "rotowire_slug": "terry-rozier-3736",
    "rotowire_id": "3736"
  },
  "3078576": {
    "espn_name": "Derrick White",
    "rotowire_slug": "derrick-white-4195",
    "rotowire_id": "4195"
  },
  "3102528": {
    "espn_name": "Dante Exum",
    "rotowire_slug": "dante-exum-3568",
    "rotowire_id": "3568"
  },
  "3102529": {
    "espn_name": "Clint Capela",
    "rotowire_slug": "clint-capela-3587",
    "rotowire_id": "3587"
  },
  "3102530": {
    "espn_name": "Jusuf Nurkic",
    "rotowire_slug": "jusuf-nurkic-3580",
    "rotowire_id": "3580"
  },
  "3102531": {
    "espn_name": "Kristaps Porzingis",
    "rotowire_slug": "kristaps-porzingis-3669",
    "rotowire_id": "3669"
  },
  "3102532": {
    "espn_name": "Vasilije Micic",
    "rotowire_slug": "vasilije-micic-3601",
    "rotowire_id": "3601"
  },
  "3102533": {
    "espn_name": "Thanasis Antetokounmpo",
    "rotowire_slug": "thanasis-antetokounmpo-3634",
    "rotowire_id": "3634"
  },
  "3112335": {
    "espn_name": "Nikola Jokic",
    "rotowire_slug": "nikola-jokic-3612",
    "rotowire_id": "3612"
  },
  "3133601": {
    "espn_name": "Devonte' Graham",
    "rotowire_slug": "devonte-graham-4464",
    "rotowire_id": "4464"
  },
  "3133602": {
    "espn_name": "Svi Mykhailiuk",
    "rotowire_slug": "svi-mykhailiuk-4457",
    "rotowire_id": "4457"
  },
  "3133603": {
    "espn_name": "Kelly Oubre Jr.",
    "rotowire_slug": "kelly-oubre-3721",
    "rotowire_id": "3721"
  },
  "3133626": {
    "espn_name": "Kenrich Williams",
    "rotowire_slug": "kenrich-williams-4462",
    "rotowire_id": "4462"
  },
  "3133628": {
    "espn_name": "Myles Turner",
    "rotowire_slug": "myles-turner-3725",
    "rotowire_id": "3725"
  },
  "3133635": {
    "espn_name": "Jevon Carter",
    "rotowire_slug": "jevon-carter-4456",
    "rotowire_id": "4456"
  },
  "3134903": {
    "espn_name": "Gary Payton II",
    "rotowire_slug": "gary-payton-3919",
    "rotowire_id": "3919"
  },
  "3134907": {
    "espn_name": "Kyle Kuzma",
    "rotowire_slug": "kyle-kuzma-4167",
    "rotowire_id": "4167"
  },
  "3134908": {
    "espn_name": "Jakob Poeltl",
    "rotowire_slug": "jakob-poeltl-3870",
    "rotowire_id": "3870"
  },
  "3134916": {
    "espn_name": "Jordan McLaughlin",
    "rotowire_slug": "jordan-mclaughlin-4533",
    "rotowire_id": "4533"
  },
  "3134932": {
    "espn_name": "John Konchar",
    "rotowire_slug": "john-konchar-4864",
    "rotowire_id": "4864"
  },
  "3135045": {
    "espn_name": "Grayson Allen",
    "rotowire_slug": "grayson-allen-4454",
    "rotowire_id": "4454"
  },
  "3135046": {
    "espn_name": "Tyus Jones",
    "rotowire_slug": "tyus-jones-3739",
    "rotowire_id": "3739"
  },
  "3135048": {
    "espn_name": "Jahlil Okafor",
    "rotowire_slug": "jahlil-okafor-3742",
    "rotowire_id": "3742"
  },
  "3136193": {
    "espn_name": "Devin Booker",
    "rotowire_slug": "devin-booker-3711",
    "rotowire_id": "3711"
  },
  "3136195": {
    "espn_name": "Karl-Anthony Towns",
    "rotowire_slug": "karl-anthony-towns-3741",
    "rotowire_id": "3741"
  },
  "3136196": {
    "espn_name": "Trey Lyles",
    "rotowire_slug": "trey-lyles-3738",
    "rotowire_id": "3738"
  },
  "3136776": {
    "espn_name": "D'Angelo Russell",
    "rotowire_slug": "dangelo-russell-3708",
    "rotowire_id": "3708"
  },
  "3136777": {
    "espn_name": "Jae'Sean Tate",
    "rotowire_slug": "jaesean-tate-4599",
    "rotowire_id": "4599"
  },
  "3136779": {
    "espn_name": "Keita Bates-Diop",
    "rotowire_slug": "keita-bates-diop-4378",
    "rotowire_id": "4378"
  },
  "3137259": {
    "espn_name": "Gabe Vincent",
    "rotowire_slug": "gabe-vincent-4631",
    "rotowire_id": "4631"
  },
  "3138160": {
    "espn_name": "Caleb Martin",
    "rotowire_slug": "caleb-martin-4931",
    "rotowire_id": "4931"
  },
  "3138161": {
    "espn_name": "Cody Martin",
    "rotowire_slug": "cody-martin-4929",
    "rotowire_id": "4929"
  },
  "3138196": {
    "espn_name": "Cameron Johnson",
    "rotowire_slug": "cameron-johnson-4916",
    "rotowire_id": "4916"
  },
  "3146557": {
    "espn_name": "Jock Landale",
    "rotowire_slug": "jock-landale-4562",
    "rotowire_id": "4562"
  },
  "3147657": {
    "espn_name": "Mikal Bridges",
    "rotowire_slug": "mikal-bridges-4386",
    "rotowire_id": "4386"
  },
  "3149673": {
    "espn_name": "Pascal Siakam",
    "rotowire_slug": "pascal-siakam-3922",
    "rotowire_id": "3922"
  },
  "3150844": {
    "espn_name": "Moritz Wagner",
    "rotowire_slug": "moritz-wagner-4389",
    "rotowire_id": "4389"
  },
  "3155526": {
    "espn_name": "Dillon Brooks",
    "rotowire_slug": "dillon-brooks-4125",
    "rotowire_id": "4125"
  },
  "3155535": {
    "espn_name": "Kevon Looney",
    "rotowire_slug": "kevon-looney-3722",
    "rotowire_id": "3722"
  },
  "3155942": {
    "espn_name": "Domantas Sabonis",
    "rotowire_slug": "domantas-sabonis-3865",
    "rotowire_id": "3865"
  },
  "3157465": {
    "espn_name": "Duncan Robinson",
    "rotowire_slug": "duncan-robinson-4470",
    "rotowire_id": "4470"
  },
  "3195": {
    "espn_name": "Mike Conley",
    "rotowire_slug": "mike-conley-2813",
    "rotowire_id": "2813"
  },
  "3202": {
    "espn_name": "Kevin Durant",
    "rotowire_slug": "kevin-durant-2811",
    "rotowire_id": "2811"
  },
  "3209": {
    "espn_name": "Jeff Green",
    "rotowire_slug": "jeff-green-2818",
    "rotowire_id": "2818"
  },
  "3213": {
    "espn_name": "Al Horford",
    "rotowire_slug": "al-horford-2816",
    "rotowire_id": "2816"
  },
  "3416": {
    "espn_name": "Nicolas Batum",
    "rotowire_slug": "nicolas-batum-2821",
    "rotowire_id": "2821"
  },
  "3431": {
    "espn_name": "Eric Gordon",
    "rotowire_slug": "eric-gordon-2926",
    "rotowire_id": "2926"
  },
  "3442": {
    "espn_name": "DeAndre Jordan",
    "rotowire_slug": "deandre-jordan-2929",
    "rotowire_id": "2929"
  },
  "3448": {
    "espn_name": "Brook Lopez",
    "rotowire_slug": "brook-lopez-2918",
    "rotowire_id": "2918"
  },
  "3449": {
    "espn_name": "Kevin Love",
    "rotowire_slug": "kevin-love-2931",
    "rotowire_id": "2931"
  },
  "3468": {
    "espn_name": "Russell Westbrook",
    "rotowire_slug": "russell-westbrook-2932",
    "rotowire_id": "2932"
  },
  "3893059": {
    "espn_name": "Anzejs Pasecniks",
    "rotowire_slug": "anzejs-pasecniks-4137",
    "rotowire_id": "4137"
  },
  "3899664": {
    "espn_name": "Simone Fontecchio",
    "rotowire_slug": "simone-fontecchio-5797",
    "rotowire_id": "5797"
  },
  "3904625": {
    "espn_name": "Tacko Fall",
    "rotowire_slug": "tacko-fall-4855",
    "rotowire_id": "4855"
  },
  "3906665": {
    "espn_name": "Brandon Clarke",
    "rotowire_slug": "brandon-clarke-4819",
    "rotowire_id": "4819"
  },
  "3907387": {
    "espn_name": "Ben Simmons",
    "rotowire_slug": "ben-simmons-3849",
    "rotowire_id": "3849"
  },
  "3907497": {
    "espn_name": "Dejounte Murray",
    "rotowire_slug": "dejounte-murray-3856",
    "rotowire_id": "3856"
  },
  "3907498": {
    "espn_name": "Matisse Thybulle",
    "rotowire_slug": "matisse-thybulle-4802",
    "rotowire_id": "4802"
  },
  "3907822": {
    "espn_name": "Malik Beasley",
    "rotowire_slug": "malik-beasley-3853",
    "rotowire_id": "3853"
  },
  "3907823": {
    "espn_name": "Terance Mann",
    "rotowire_slug": "terance-mann-4860",
    "rotowire_id": "4860"
  },
  "3908336": {
    "espn_name": "Matt Ryan",
    "rotowire_slug": "matt-ryan-5268",
    "rotowire_id": "5268"
  },
  "3908809": {
    "espn_name": "Donovan Mitchell",
    "rotowire_slug": "donovan-mitchell-4166",
    "rotowire_id": "4166"
  },
  "3908845": {
    "espn_name": "John Collins",
    "rotowire_slug": "john-collins-4159",
    "rotowire_id": "4159"
  },
  "3911893": {
    "espn_name": "Jack McVeigh",
    "rotowire_slug": "jack-mcveigh-4422",
    "rotowire_id": "4422"
  },
  "3912848": {
    "espn_name": "Dean Wade",
    "rotowire_slug": "dean-wade-4893",
    "rotowire_id": "4893"
  },
  "3913174": {
    "espn_name": "Luke Kennard",
    "rotowire_slug": "luke-kennard-4123",
    "rotowire_id": "4123"
  },
  "3913176": {
    "espn_name": "Brandon Ingram",
    "rotowire_slug": "brandon-ingram-3861",
    "rotowire_id": "3861"
  },
  "3913180": {
    "espn_name": "Garrison Mathews",
    "rotowire_slug": "garrison-mathews-4990",
    "rotowire_id": "4990"
  },
  "3913220": {
    "espn_name": "DaQuan Jeffries",
    "rotowire_slug": "daquan-jeffries-4937",
    "rotowire_id": "4937"
  },
  "3914044": {
    "espn_name": "Landry Shamet",
    "rotowire_slug": "landry-shamet-4414",
    "rotowire_id": "4414"
  },
  "3914285": {
    "espn_name": "Drew Eubanks",
    "rotowire_slug": "drew-eubanks-4416",
    "rotowire_id": "4416"
  },
  "3915195": {
    "espn_name": "Shake Milton",
    "rotowire_slug": "shake-milton-4443",
    "rotowire_id": "4443"
  },
  "3917376": {
    "espn_name": "Jaylen Brown",
    "rotowire_slug": "jaylen-brown-3894",
    "rotowire_id": "3894"
  },
  "3919454": {
    "espn_name": "Terence Davis",
    "rotowire_slug": "terence-davis-4842",
    "rotowire_id": "4842"
  },
  "3922230": {
    "espn_name": "Aaron Holiday",
    "rotowire_slug": "aaron-holiday-4380",
    "rotowire_id": "4380"
  },
  "3923250": {
    "espn_name": "PJ Dozier",
    "rotowire_slug": "pj-dozier-4127",
    "rotowire_id": "4127"
  },
  "3934672": {
    "espn_name": "Jalen Brunson",
    "rotowire_slug": "jalen-brunson-4405",
    "rotowire_id": "4405"
  },
  "3934673": {
    "espn_name": "Donte DiVincenzo",
    "rotowire_slug": "donte-divincenzo-4439",
    "rotowire_id": "4439"
  },
  "3934719": {
    "espn_name": "OG Anunoby",
    "rotowire_slug": "og-anunoby-4121",
    "rotowire_id": "4121"
  },
  "3934723": {
    "espn_name": "Thomas Bryant",
    "rotowire_slug": "thomas-bryant-4155",
    "rotowire_id": "4155"
  },
  "3936099": {
    "espn_name": "Derrick Jones Jr.",
    "rotowire_slug": "derrick-jones-4083",
    "rotowire_id": "4083"
  },
  "3936296": {
    "espn_name": "Skal Labissiere",
    "rotowire_slug": "skal-labissiere-3863",
    "rotowire_id": "3863"
  },
  "3936299": {
    "espn_name": "Jamal Murray",
    "rotowire_slug": "jamal-murray-3882",
    "rotowire_id": "3882"
  },
  "3945274": {
    "espn_name": "Luka Doncic",
    "rotowire_slug": "luka-doncic-4396",
    "rotowire_id": "4396"
  },
  "3947156": {
    "espn_name": "Mamadi Diakite",
    "rotowire_slug": "mamadi-diakite-5203",
    "rotowire_id": "5203"
  },
  "3948153": {
    "espn_name": "Chris Boucher",
    "rotowire_slug": "chris-boucher-4143",
    "rotowire_id": "4143"
  },
  "3950760": {
    "espn_name": "Kylor Kelley",
    "rotowire_slug": "kylor-kelley-5316",
    "rotowire_id": "5316"
  },
  "3975": {
    "espn_name": "Stephen Curry",
    "rotowire_slug": "stephen-curry-3014",
    "rotowire_id": "3014"
  },
  "3978": {
    "espn_name": "DeMar DeRozan",
    "rotowire_slug": "demar-derozan-3019",
    "rotowire_id": "3019"
  },
  "3986": {
    "espn_name": "Taj Gibson",
    "rotowire_slug": "taj-gibson-3035",
    "rotowire_id": "3035"
  },
  "3992": {
    "espn_name": "James Harden",
    "rotowire_slug": "james-harden-3018",
    "rotowire_id": "3018"
  },
  "3995": {
    "espn_name": "Jrue Holiday",
    "rotowire_slug": "jrue-holiday-3029",
    "rotowire_id": "3029"
  },
  "3999": {
    "espn_name": "James Johnson",
    "rotowire_slug": "james-johnson-3021",
    "rotowire_id": "3021"
  },
  "4004": {
    "espn_name": "Patty Mills",
    "rotowire_slug": "patty-mills-3027",
    "rotowire_id": "3027"
  },
  "4017837": {
    "espn_name": "Ivica Zubac",
    "rotowire_slug": "ivica-zubac-3888",
    "rotowire_id": "3888"
  },
  "4017843": {
    "espn_name": "Thon Maker",
    "rotowire_slug": "thon-maker-3860",
    "rotowire_id": "3860"
  },
  "4017844": {
    "espn_name": "Guerschon Yabusele",
    "rotowire_slug": "guerschon-yabusele-3932",
    "rotowire_id": "3932"
  },
  "4023": {
    "espn_name": "Garrett Temple",
    "rotowire_slug": "garrett-temple-3083",
    "rotowire_id": "3083"
  },
  "4065648": {
    "espn_name": "Jayson Tatum",
    "rotowire_slug": "jayson-tatum-4108",
    "rotowire_id": "4108"
  },
  "4065649": {
    "espn_name": "Harry Giles III",
    "rotowire_slug": "harry-giles-4111",
    "rotowire_id": "4111"
  },
  "4065652": {
    "espn_name": "Marques Bolden",
    "rotowire_slug": "marques-bolden-4818",
    "rotowire_id": "4818"
  },
  "4065654": {
    "espn_name": "Jonathan Isaac",
    "rotowire_slug": "jonathan-isaac-4103",
    "rotowire_id": "4103"
  },
  "4065663": {
    "espn_name": "Josh Okogie",
    "rotowire_slug": "josh-okogie-4436",
    "rotowire_id": "4436"
  },
  "4065670": {
    "espn_name": "Bruce Brown",
    "rotowire_slug": "bruce-brown-4403",
    "rotowire_id": "4403"
  },
  "4065673": {
    "espn_name": "Tony Bradley",
    "rotowire_slug": "tony-bradley-4170",
    "rotowire_id": "4170"
  },
  "4065697": {
    "espn_name": "Dennis Smith Jr.",
    "rotowire_slug": "dennis-smith-4109",
    "rotowire_id": "4109"
  },
  "4065731": {
    "espn_name": "Jay Huff",
    "rotowire_slug": "jay-huff-5339",
    "rotowire_id": "5339"
  },
  "4065732": {
    "espn_name": "De'Andre Hunter",
    "rotowire_slug": "deandre-hunter-4776",
    "rotowire_id": "4776"
  },
  "4065733": {
    "espn_name": "Ty Jerome",
    "rotowire_slug": "ty-jerome-4774",
    "rotowire_id": "4774"
  },
  "4065778": {
    "espn_name": "Max Strus",
    "rotowire_slug": "max-strus-4947",
    "rotowire_id": "4947"
  },
  "4065804": {
    "espn_name": "Sam Hauser",
    "rotowire_slug": "sam-hauser-5338",
    "rotowire_id": "5338"
  },
  "4066211": {
    "espn_name": "Robert Williams III",
    "rotowire_slug": "robert-williams-4382",
    "rotowire_id": "4382"
  },
  "4066218": {
    "espn_name": "Grant Williams",
    "rotowire_slug": "grant-williams-4814",
    "rotowire_id": "4814"
  },
  "4066240": {
    "espn_name": "Braxton Key",
    "rotowire_slug": "braxton-key-5324",
    "rotowire_id": "5324"
  },
  "4066248": {
    "espn_name": "Jared Harper",
    "rotowire_slug": "jared-harper-4769",
    "rotowire_id": "4769"
  },
  "4066259": {
    "espn_name": "De'Aaron Fox",
    "rotowire_slug": "deaaron-fox-4116",
    "rotowire_id": "4116"
  },
  "4066261": {
    "espn_name": "Bam Adebayo",
    "rotowire_slug": "bam-adebayo-4153",
    "rotowire_id": "4153"
  },
  "4066262": {
    "espn_name": "Malik Monk",
    "rotowire_slug": "malik-monk-4117",
    "rotowire_id": "4117"
  },
  "4066268": {
    "espn_name": "Duop Reath",
    "rotowire_slug": "duop-reath-4546",
    "rotowire_id": "4546"
  },
  "4066269": {
    "espn_name": "Skylar Mays",
    "rotowire_slug": "skylar-mays-5296",
    "rotowire_id": "5296"
  },
  "4066317": {
    "espn_name": "Lindy Waters III",
    "rotowire_slug": "lindy-waters-5610",
    "rotowire_id": "5610"
  },
  "4066320": {
    "espn_name": "Desmond Bane",
    "rotowire_slug": "desmond-bane-5159",
    "rotowire_id": "5159"
  },
  "4066328": {
    "espn_name": "Jarrett Allen",
    "rotowire_slug": "jarrett-allen-4122",
    "rotowire_id": "4122"
  },
  "4066336": {
    "espn_name": "Lauri Markkanen",
    "rotowire_slug": "lauri-markkanen-4119",
    "rotowire_id": "4119"
  },
  "4066354": {
    "espn_name": "Payton Pritchard",
    "rotowire_slug": "payton-pritchard-5131",
    "rotowire_id": "5131"
  },
  "4066372": {
    "espn_name": "Kevin Huerter",
    "rotowire_slug": "kevin-huerter-4449",
    "rotowire_id": "4449"
  },
  "4066382": {
    "espn_name": "Cassius Winston",
    "rotowire_slug": "cassius-winston-5144",
    "rotowire_id": "5144"
  },
  "4066383": {
    "espn_name": "Miles Bridges",
    "rotowire_slug": "miles-bridges-4383",
    "rotowire_id": "4383"
  },
  "4066387": {
    "espn_name": "Amir Coffey",
    "rotowire_slug": "amir-coffey-4836",
    "rotowire_id": "4836"
  },
  "4066399": {
    "espn_name": "Micah Potter",
    "rotowire_slug": "micah-potter-5445",
    "rotowire_id": "5445"
  },
  "4066405": {
    "espn_name": "Lamar Stevens",
    "rotowire_slug": "lamar-stevens-5294",
    "rotowire_id": "5294"
  },
  "4066410": {
    "espn_name": "Eugene Omoruyi",
    "rotowire_slug": "eugene-omoruyi-5372",
    "rotowire_id": "5372"
  },
  "4066421": {
    "espn_name": "Lonzo Ball",
    "rotowire_slug": "lonzo-ball-4110",
    "rotowire_id": "4110"
  },
  "4066436": {
    "espn_name": "De'Anthony Melton",
    "rotowire_slug": "deanthony-melton-4368",
    "rotowire_id": "4368"
  },
  "4066457": {
    "espn_name": "Austin Reaves",
    "rotowire_slug": "austin-reaves-5334",
    "rotowire_id": "5334"
  },
  "4066486": {
    "espn_name": "Jarron Cumberland",
    "rotowire_slug": "jarron-cumberland-5150",
    "rotowire_id": "5150"
  },
  "4066508": {
    "espn_name": "Charlie Brown Jr.",
    "rotowire_slug": "charlie-brown-4829",
    "rotowire_id": "4829"
  },
  "4066636": {
    "espn_name": "Markelle Fultz",
    "rotowire_slug": "markelle-fultz-4100",
    "rotowire_id": "4100"
  },
  "4066648": {
    "espn_name": "Rui Hachimura",
    "rotowire_slug": "rui-hachimura-4778",
    "rotowire_id": "4778"
  },
  "4066650": {
    "espn_name": "Zach Collins",
    "rotowire_slug": "zach-collins-4162",
    "rotowire_id": "4162"
  },
  "4066668": {
    "espn_name": "Malachi Flynn",
    "rotowire_slug": "malachi-flynn-5231",
    "rotowire_id": "5231"
  },
  "4066731": {
    "espn_name": "Jalen McDaniels",
    "rotowire_slug": "jalen-mcdaniels-4908",
    "rotowire_id": "4908"
  },
  "4066757": {
    "espn_name": "Sam Merrill",
    "rotowire_slug": "sam-merrill-5254",
    "rotowire_id": "5254"
  },
  "4066786": {
    "espn_name": "Jeff Dowtin Jr.",
    "rotowire_slug": "jeff-dowtin-5132",
    "rotowire_id": "5132"
  },
  "4066790": {
    "espn_name": "Anthony Lamb",
    "rotowire_slug": "anthony-lamb-5165",
    "rotowire_id": "5165"
  },
  "4066808": {
    "espn_name": "Taze Moore",
    "rotowire_slug": "taze-moore-5788",
    "rotowire_id": "5788"
  },
  "4066851": {
    "espn_name": "Miye Oni",
    "rotowire_slug": "miye-oni-4861",
    "rotowire_id": "4861"
  },
  "4066889": {
    "espn_name": "Jackson Rowe",
    "rotowire_slug": "jackson-rowe-6227",
    "rotowire_id": "6227"
  },
  "4066993": {
    "espn_name": "Dru Smith",
    "rotowire_slug": "dru-smith-5352",
    "rotowire_id": "5352"
  },
  "4067017": {
    "espn_name": "A.J. Lawson",
    "rotowire_slug": "aj-lawson-5398",
    "rotowire_id": "5398"
  },
  "4067045": {
    "espn_name": "Alize Johnson",
    "rotowire_slug": "alize-johnson-4461",
    "rotowire_id": "4461"
  },
  "4067069": {
    "espn_name": "Nate Darling",
    "rotowire_slug": "nate-darling-5303",
    "rotowire_id": "5303"
  },
  "4067858": {
    "espn_name": "Kevon Harris",
    "rotowire_slug": "kevon-harris-5314",
    "rotowire_id": "5314"
  },
  "4222252": {
    "espn_name": "Isaiah Hartenstein",
    "rotowire_slug": "isaiah-hartenstein-4147",
    "rotowire_id": "4147"
  },
  "4230557": {
    "espn_name": "Vlatko Cancar",
    "rotowire_slug": "vlatko-cancar-4179",
    "rotowire_id": "4179"
  },
  "4251": {
    "espn_name": "Paul George",
    "rotowire_slug": "paul-george-3114",
    "rotowire_id": "3114"
  },
  "4277811": {
    "espn_name": "Collin Sexton",
    "rotowire_slug": "collin-sexton-4412",
    "rotowire_id": "4412"
  },
  "4277812": {
    "espn_name": "Alex Reese",
    "rotowire_slug": "alex-reese-6223",
    "rotowire_id": "6223"
  },
  "4277813": {
    "espn_name": "Herbert Jones",
    "rotowire_slug": "herbert-jones-5414",
    "rotowire_id": "5414"
  },
  "4277843": {
    "espn_name": "Gary Trent Jr.",
    "rotowire_slug": "gary-trent-4433",
    "rotowire_id": "4433"
  },
  "4277847": {
    "espn_name": "Wendell Carter Jr.",
    "rotowire_slug": "wendell-carter-4407",
    "rotowire_id": "4407"
  },
  "4277848": {
    "espn_name": "Marvin Bagley III",
    "rotowire_slug": "marvin-bagley-4397",
    "rotowire_id": "4397"
  },
  "4277854": {
    "espn_name": "MJ Walker",
    "rotowire_slug": "mj-walker-5465",
    "rotowire_id": "5465"
  },
  "4277869": {
    "espn_name": "Jose Alvarado",
    "rotowire_slug": "jose-alvarado-5424",
    "rotowire_id": "5424"
  },
  "4277880": {
    "espn_name": "Malik Williams",
    "rotowire_slug": "malik-williams-6239",
    "rotowire_id": "6239"
  },
  "4277890": {
    "espn_name": "Lonnie Walker IV",
    "rotowire_slug": "lonnie-walker-4435",
    "rotowire_id": "4435"
  },
  "4277892": {
    "espn_name": "Marcus Garrett",
    "rotowire_slug": "marcus-garrett-5422",
    "rotowire_id": "5422"
  },
  "4277905": {
    "espn_name": "Trae Young",
    "rotowire_slug": "trae-young-4369",
    "rotowire_id": "4369"
  },
  "4277919": {
    "espn_name": "Mo Bamba",
    "rotowire_slug": "mo-bamba-4371",
    "rotowire_id": "4371"
  },
  "4277922": {
    "espn_name": "Jericho Sims",
    "rotowire_slug": "jericho-sims-5389",
    "rotowire_id": "5389"
  },
  "4277923": {
    "espn_name": "Zhaire Smith",
    "rotowire_slug": "zhaire-smith-4445",
    "rotowire_id": "4445"
  },
  "4277928": {
    "espn_name": "Jarrett Culver",
    "rotowire_slug": "jarrett-culver-4813",
    "rotowire_id": "4813"
  },
  "4277951": {
    "espn_name": "Luka Garza",
    "rotowire_slug": "luka-garza-5423",
    "rotowire_id": "5423"
  },
  "4277952": {
    "espn_name": "Bruno Fernando",
    "rotowire_slug": "bruno-fernando-4799",
    "rotowire_id": "4799"
  },
  "4277956": {
    "espn_name": "Jordan Poole",
    "rotowire_slug": "jordan-poole-4791",
    "rotowire_id": "4791"
  },
  "4277957": {
    "espn_name": "Isaiah Livers",
    "rotowire_slug": "isaiah-livers-5353",
    "rotowire_id": "5353"
  },
  "4277961": {
    "espn_name": "Jaren Jackson Jr.",
    "rotowire_slug": "jaren-jackson-4384",
    "rotowire_id": "4384"
  },
  "4277964": {
    "espn_name": "Xavier Tillman",
    "rotowire_slug": "xavier-tillman-5290",
    "rotowire_id": "5290"
  },
  "4278031": {
    "espn_name": "Oshae Brissett",
    "rotowire_slug": "oshae-brissett-4816",
    "rotowire_id": "4816"
  },
  "4278039": {
    "espn_name": "Nickeil Alexander-Walker",
    "rotowire_slug": "nickeil-alexander-walker-4765",
    "rotowire_id": "4765"
  },
  "4278046": {
    "espn_name": "Olivier Sarr",
    "rotowire_slug": "olivier-sarr-5494",
    "rotowire_id": "5494"
  },
  "4278049": {
    "espn_name": "Daniel Gafford",
    "rotowire_slug": "daniel-gafford-4824",
    "rotowire_id": "4824"
  },
  "4278052": {
    "espn_name": "Chuma Okeke",
    "rotowire_slug": "chuma-okeke-4805",
    "rotowire_id": "4805"
  },
  "4278053": {
    "espn_name": "Davion Mitchell",
    "rotowire_slug": "davion-mitchell-5354",
    "rotowire_id": "5354"
  },
  "4278067": {
    "espn_name": "Nic Claxton",
    "rotowire_slug": "nic-claxton-4827",
    "rotowire_id": "4827"
  },
  "4278073": {
    "espn_name": "Shai Gilgeous-Alexander",
    "rotowire_slug": "shai-gilgeous-alexander-4387",
    "rotowire_id": "4387"
  },
  "4278075": {
    "espn_name": "Kevin Knox II",
    "rotowire_slug": "kevin-knox-4398",
    "rotowire_id": "4398"
  },
  "4278076": {
    "espn_name": "Nick Richards",
    "rotowire_slug": "nick-richards-5212",
    "rotowire_id": "5212"
  },
  "4278077": {
    "espn_name": "Jarred Vanderbilt",
    "rotowire_slug": "jarred-vanderbilt-4458",
    "rotowire_id": "4458"
  },
  "4278078": {
    "espn_name": "P.J. Washington",
    "rotowire_slug": "pj-washington-4781",
    "rotowire_id": "4781"
  },
  "4278104": {
    "espn_name": "Michael Porter Jr.",
    "rotowire_slug": "michael-porter-4375",
    "rotowire_id": "4375"
  },
  "4278111": {
    "espn_name": "Justin Minaya",
    "rotowire_slug": "justin-minaya-5691",
    "rotowire_id": "5691"
  },
  "4278129": {
    "espn_name": "Deandre Ayton",
    "rotowire_slug": "deandre-ayton-4372",
    "rotowire_id": "4372"
  },
  "4278352": {
    "espn_name": "Jalen Crutcher",
    "rotowire_slug": "jalen-crutcher-5454",
    "rotowire_id": "5454"
  },
  "4278355": {
    "espn_name": "Obi Toppin",
    "rotowire_slug": "obi-toppin-5109",
    "rotowire_id": "5109"
  },
  "4278378": {
    "espn_name": "Jacob Gilyard",
    "rotowire_slug": "jacob-gilyard-5763",
    "rotowire_id": "5763"
  },
  "4278402": {
    "espn_name": "Jordan Goodwin",
    "rotowire_slug": "jordan-goodwin-5460",
    "rotowire_id": "5460"
  },
  "4278516": {
    "espn_name": "Ethan Thompson",
    "rotowire_slug": "ethan-thompson-5449",
    "rotowire_id": "5449"
  },
  "4278541": {
    "espn_name": "Jaylen Nowell",
    "rotowire_slug": "jaylen-nowell-4803",
    "rotowire_id": "4803"
  },
  "4278562": {
    "espn_name": "Paul Reed",
    "rotowire_slug": "paul-reed-5124",
    "rotowire_id": "5124"
  },
  "4278572": {
    "espn_name": "Jamal Cain",
    "rotowire_slug": "jamal-cain-5796",
    "rotowire_id": "5796"
  },
  "4278580": {
    "espn_name": "Sandro Mamukelashvili",
    "rotowire_slug": "sandro-mamukelashvili-5341",
    "rotowire_id": "5341"
  },
  "4278585": {
    "espn_name": "Collin Gillespie",
    "rotowire_slug": "collin-gillespie-5732",
    "rotowire_id": "5732"
  },
  "4278588": {
    "espn_name": "Jermaine Samuels Jr.",
    "rotowire_slug": "jermaine-samuels-5753",
    "rotowire_id": "5753"
  },
  "4278594": {
    "espn_name": "Naji Marshall",
    "rotowire_slug": "naji-marshall-5204",
    "rotowire_id": "5204"
  },
  "4279118": {
    "espn_name": "Keaton Wallace",
    "rotowire_slug": "keaton-wallace-5453",
    "rotowire_id": "5453"
  },
  "4279318": {
    "espn_name": "Daeqwon Plowden",
    "rotowire_slug": "daeqwon-plowden-5800",
    "rotowire_id": "5800"
  },
  "4279532": {
    "espn_name": "Stanley Umude",
    "rotowire_slug": "stanley-umude-5815",
    "rotowire_id": "5815"
  },
  "4279815": {
    "espn_name": "Terry Taylor",
    "rotowire_slug": "terry-taylor-5399",
    "rotowire_id": "5399"
  },
  "4279888": {
    "espn_name": "Ja Morant",
    "rotowire_slug": "ja-morant-4761",
    "rotowire_id": "4761"
  },
  "4280151": {
    "espn_name": "Corey Kispert",
    "rotowire_slug": "corey-kispert-5387",
    "rotowire_id": "5387"
  },
  "4280245": {
    "espn_name": "Jamaree Bouyea",
    "rotowire_slug": "jamaree-bouyea-5725",
    "rotowire_id": "5725"
  },
  "4291678": {
    "espn_name": "Haywood Highsmith",
    "rotowire_slug": "haywood-highsmith-4583",
    "rotowire_id": "4583"
  },
  "4348700": {
    "espn_name": "Goga Bitadze",
    "rotowire_slug": "goga-bitadze-4914",
    "rotowire_id": "4914"
  },
  "4351851": {
    "espn_name": "Anfernee Simons",
    "rotowire_slug": "anfernee-simons-4373",
    "rotowire_id": "4373"
  },
  "4351852": {
    "espn_name": "Mitchell Robinson",
    "rotowire_slug": "mitchell-robinson-4426",
    "rotowire_id": "4426"
  },
  "4395620": {
    "espn_name": "Hunter Tyson",
    "rotowire_slug": "hunter-tyson-6002",
    "rotowire_id": "6002"
  },
  "4395623": {
    "espn_name": "Trey Jemison III",
    "rotowire_slug": "trey-jemison-6151",
    "rotowire_id": "6151"
  },
  "4395625": {
    "espn_name": "RJ Barrett",
    "rotowire_slug": "rj-barrett-4767",
    "rotowire_id": "4767"
  },
  "4395626": {
    "espn_name": "Tre Jones",
    "rotowire_slug": "tre-jones-5111",
    "rotowire_id": "5111"
  },
  "4395627": {
    "espn_name": "Cam Reddish",
    "rotowire_slug": "cam-reddish-4772",
    "rotowire_id": "4772"
  },
  "4395628": {
    "espn_name": "Zion Williamson",
    "rotowire_slug": "zion-williamson-4777",
    "rotowire_id": "4777"
  },
  "4395630": {
    "espn_name": "Devin Vassell",
    "rotowire_slug": "devin-vassell-5113",
    "rotowire_id": "5113"
  },
  "4395650": {
    "espn_name": "Leaky Black",
    "rotowire_slug": "leaky-black-5953",
    "rotowire_id": "5953"
  },
  "4395651": {
    "espn_name": "Coby White",
    "rotowire_slug": "coby-white-4801",
    "rotowire_id": "4801"
  },
  "4395652": {
    "espn_name": "Nassir Little",
    "rotowire_slug": "nassir-little-4760",
    "rotowire_id": "4760"
  },
  "4395676": {
    "espn_name": "Buddy Boeheim",
    "rotowire_slug": "buddy-boeheim-5672",
    "rotowire_id": "5672"
  },
  "4395695": {
    "espn_name": "Jared Butler",
    "rotowire_slug": "jared-butler-5295",
    "rotowire_id": "5295"
  },
  "4395698": {
    "espn_name": "Kira Lewis Jr.",
    "rotowire_slug": "kira-lewis-5242",
    "rotowire_id": "5242"
  },
  "4395702": {
    "espn_name": "Isaiah Joe",
    "rotowire_slug": "isaiah-joe-5291",
    "rotowire_id": "5291"
  },
  "4395704": {
    "espn_name": "Mason Jones",
    "rotowire_slug": "mason-jones-5297",
    "rotowire_id": "5297"
  },
  "4395712": {
    "espn_name": "Andrew Nembhard",
    "rotowire_slug": "andrew-nembhard-5679",
    "rotowire_id": "5679"
  },
  "4395714": {
    "espn_name": "Keyontae Johnson",
    "rotowire_slug": "keyontae-johnson-5963",
    "rotowire_id": "5963"
  },
  "4395723": {
    "espn_name": "Keldon Johnson",
    "rotowire_slug": "keldon-johnson-4782",
    "rotowire_id": "4782"
  },
  "4395724": {
    "espn_name": "Immanuel Quickley",
    "rotowire_slug": "immanuel-quickley-5201",
    "rotowire_id": "5201"
  },
  "4395725": {
    "espn_name": "Tyler Herro",
    "rotowire_slug": "tyler-herro-4780",
    "rotowire_id": "4780"
  },
  "4396629": {
    "espn_name": "Nate Hinton",
    "rotowire_slug": "nate-hinton-5274",
    "rotowire_id": "5274"
  },
  "4396676": {
    "espn_name": "Dexter Dennis",
    "rotowire_slug": "dexter-dennis-6102",
    "rotowire_id": "6102"
  },
  "4396679": {
    "espn_name": "Erik Stevenson",
    "rotowire_slug": "erik-stevenson-6091",
    "rotowire_id": "6091"
  },
  "4396818": {
    "espn_name": "Jordan Miller",
    "rotowire_slug": "jordan-miller-6018",
    "rotowire_id": "6018"
  },
  "4396907": {
    "espn_name": "Darius Garland",
    "rotowire_slug": "darius-garland-4749",
    "rotowire_id": "4749"
  },
  "4396909": {
    "espn_name": "Aaron Nesmith",
    "rotowire_slug": "aaron-nesmith-5120",
    "rotowire_id": "5120"
  },
  "4396971": {
    "espn_name": "Naz Reid",
    "rotowire_slug": "naz-reid-4806",
    "rotowire_id": "4806"
  },
  "4396972": {
    "espn_name": "Javonte Smart",
    "rotowire_slug": "javonte-smart-5361",
    "rotowire_id": "5361"
  },
  "4396991": {
    "espn_name": "Talen Horton-Tucker",
    "rotowire_slug": "talen-horton-tucker-4821",
    "rotowire_id": "4821"
  },
  "4396993": {
    "espn_name": "Tyrese Haliburton",
    "rotowire_slug": "tyrese-haliburton-5114",
    "rotowire_id": "5114"
  },
  "4397002": {
    "espn_name": "Ayo Dosunmu",
    "rotowire_slug": "ayo-dosunmu-5337",
    "rotowire_id": "5337"
  },
  "4397014": {
    "espn_name": "Quentin Grimes",
    "rotowire_slug": "quentin-grimes-5391",
    "rotowire_id": "5391"
  },
  "4397018": {
    "espn_name": "Ochai Agbaji",
    "rotowire_slug": "ochai-agbaji-5683",
    "rotowire_id": "5683"
  },
  "4397020": {
    "espn_name": "Luguentz Dort",
    "rotowire_slug": "luguentz-dort-4808",
    "rotowire_id": "4808"
  },
  "4397040": {
    "espn_name": "Brandon Williams",
    "rotowire_slug": "brandon-williams-5588",
    "rotowire_id": "5588"
  },
  "4397071": {
    "espn_name": "Mac McClung",
    "rotowire_slug": "mac-mcclung-5375",
    "rotowire_id": "5375"
  },
  "4397077": {
    "espn_name": "Jaxson Hayes",
    "rotowire_slug": "jaxson-hayes-4771",
    "rotowire_id": "4771"
  },
  "4397102": {
    "espn_name": "Bol Bol",
    "rotowire_slug": "bol-bol-4759",
    "rotowire_id": "4759"
  },
  "4397104": {
    "espn_name": "Miles Norris",
    "rotowire_slug": "miles-norris-6070",
    "rotowire_id": "6070"
  },
  "4397107": {
    "espn_name": "David Duke Jr.",
    "rotowire_slug": "david-duke-5346",
    "rotowire_id": "5346"
  },
  "4397119": {
    "espn_name": "Jared Rhoden",
    "rotowire_slug": "jared-rhoden-5658",
    "rotowire_id": "5658"
  },
  "4397126": {
    "espn_name": "Moses Brown",
    "rotowire_slug": "moses-brown-4811",
    "rotowire_id": "4811"
  },
  "4397127": {
    "espn_name": "Jules Bernard",
    "rotowire_slug": "jules-bernard-5671",
    "rotowire_id": "5671"
  },
  "4397134": {
    "espn_name": "Cole Swider",
    "rotowire_slug": "cole-swider-5638",
    "rotowire_id": "5638"
  },
  "4397136": {
    "espn_name": "Saddiq Bey",
    "rotowire_slug": "saddiq-bey-5182",
    "rotowire_id": "5182"
  },
  "4397140": {
    "espn_name": "Kevin Porter Jr.",
    "rotowire_slug": "kevin-porter-4773",
    "rotowire_id": "4773"
  },
  "4397179": {
    "espn_name": "Tyrese Martin",
    "rotowire_slug": "tyrese-martin-5736",
    "rotowire_id": "5736"
  },
  "4397183": {
    "espn_name": "Aaron Wiggins",
    "rotowire_slug": "aaron-wiggins-5412",
    "rotowire_id": "5412"
  },
  "4397189": {
    "espn_name": "Jalen Smith",
    "rotowire_slug": "jalen-smith-5169",
    "rotowire_id": "5169"
  },
  "4397204": {
    "espn_name": "Colin Castleton",
    "rotowire_slug": "colin-castleton-5988",
    "rotowire_id": "5988"
  },
  "4397227": {
    "espn_name": "Vince Williams Jr.",
    "rotowire_slug": "vince-williams-5734",
    "rotowire_id": "5734"
  },
  "4397233": {
    "espn_name": "Pete Nance",
    "rotowire_slug": "pete-nance-6050",
    "rotowire_id": "6050"
  },
  "4397235": {
    "espn_name": "Duane Washington Jr.",
    "rotowire_slug": "duane-washington-5417",
    "rotowire_id": "5417"
  },
  "4397251": {
    "espn_name": "Ron Harper Jr.",
    "rotowire_slug": "ron-harper-5661",
    "rotowire_id": "5661"
  },
  "4397347": {
    "espn_name": "Liam Robbins",
    "rotowire_slug": "liam-robbins-6040",
    "rotowire_id": "6040"
  },
  "4397424": {
    "espn_name": "Neemias Queta",
    "rotowire_slug": "neemias-queta-5333",
    "rotowire_id": "5333"
  },
  "4397449": {
    "espn_name": "Elijah Harkless",
    "rotowire_slug": "elijah-harkless-6178",
    "rotowire_id": "6178"
  },
  "4397475": {
    "espn_name": "AJ Green",
    "rotowire_slug": "aj-green-5750",
    "rotowire_id": "5750"
  },
  "4397537": {
    "espn_name": "Taevion Kinsey",
    "rotowire_slug": "taevion-kinsey-6012",
    "rotowire_id": "6012"
  },
  "4397554": {
    "espn_name": "Markquis Nowell",
    "rotowire_slug": "markquis-nowell-5907",
    "rotowire_id": "5907"
  },
  "4397570": {
    "espn_name": "Jaylen Sims",
    "rotowire_slug": "jaylen-sims-5805",
    "rotowire_id": "5805"
  },
  "4397650": {
    "espn_name": "Andrew Funk",
    "rotowire_slug": "andrew-funk-6127",
    "rotowire_id": "6127"
  },
  "4397654": {
    "espn_name": "Adam Flagler",
    "rotowire_slug": "adam-flagler-5984",
    "rotowire_id": "5984"
  },
  "4397688": {
    "espn_name": "Trey Murphy III",
    "rotowire_slug": "trey-murphy-5401",
    "rotowire_id": "5401"
  },
  "4397689": {
    "espn_name": "Drew Peterson",
    "rotowire_slug": "drew-peterson-6027",
    "rotowire_id": "6027"
  },
  "4397693": {
    "espn_name": "Kessler Edwards",
    "rotowire_slug": "kessler-edwards-5419",
    "rotowire_id": "5419"
  },
  "4397821": {
    "espn_name": "Nate Williams",
    "rotowire_slug": "nate-williams-5777",
    "rotowire_id": "5777"
  },
  "4397882": {
    "espn_name": "Tolu Smith",
    "rotowire_slug": "tolu-smith-6354",
    "rotowire_id": "6354"
  },
  "4397885": {
    "espn_name": "Dalano Banton",
    "rotowire_slug": "dalano-banton-5430",
    "rotowire_id": "5430"
  },
  "4397886": {
    "espn_name": "Charles Bassey",
    "rotowire_slug": "charles-bassey-4833",
    "rotowire_id": "4833"
  },
  "4397916": {
    "espn_name": "Jason Preston",
    "rotowire_slug": "jason-preston-5429",
    "rotowire_id": "5429"
  },
  "4397999": {
    "espn_name": "Cameron Parker",
    "rotowire_slug": "cameron-parker-6481",
    "rotowire_id": "6481"
  },
  "4398207": {
    "espn_name": "Jalen Slawson",
    "rotowire_slug": "jalen-slawson-6034",
    "rotowire_id": "6034"
  },
  "4398390": {
    "espn_name": "Jalen Pickett",
    "rotowire_slug": "jalen-pickett-5918",
    "rotowire_id": "5918"
  },
  "4407254": {
    "espn_name": "Brodric Thomas",
    "rotowire_slug": "brodric-thomas-5319",
    "rotowire_id": "5319"
  },
  "4409222": {
    "espn_name": "Trevelin Queen",
    "rotowire_slug": "trevelin-queen-5237",
    "rotowire_id": "5237"
  },
  "4411057": {
    "espn_name": "Kevin McCullar Jr.",
    "rotowire_slug": "kevin-mccullar-5983",
    "rotowire_id": "5983"
  },
  "4431671": {
    "espn_name": "Jaden McDaniels",
    "rotowire_slug": "jaden-mcdaniels-5221",
    "rotowire_id": "5221"
  },
  "4431675": {
    "espn_name": "Trendon Watford",
    "rotowire_slug": "trendon-watford-5358",
    "rotowire_id": "5358"
  },
  "4431678": {
    "espn_name": "Tyrese Maxey",
    "rotowire_slug": "tyrese-maxey-5158",
    "rotowire_id": "5158"
  },
  "4431679": {
    "espn_name": "Precious Achiuwa",
    "rotowire_slug": "precious-achiuwa-5249",
    "rotowire_id": "5249"
  },
  "4431680": {
    "espn_name": "Onyeka Okongwu",
    "rotowire_slug": "onyeka-okongwu-5118",
    "rotowire_id": "5118"
  },
  "4431684": {
    "espn_name": "Trayce Jackson-Davis",
    "rotowire_slug": "trayce-jackson-davis-5944",
    "rotowire_id": "5944"
  },
  "4431687": {
    "espn_name": "Patrick Williams",
    "rotowire_slug": "patrick-williams-5122",
    "rotowire_id": "5122"
  },
  "4431688": {
    "espn_name": "Jahmi'us Ramsey",
    "rotowire_slug": "jahmius-ramsey-5252",
    "rotowire_id": "5252"
  },
  "4431689": {
    "espn_name": "Keion Brooks Jr.",
    "rotowire_slug": "keion-brooks-6384",
    "rotowire_id": "6384"
  },
  "4431690": {
    "espn_name": "Zeke Nnaji",
    "rotowire_slug": "zeke-nnaji-5123",
    "rotowire_id": "5123"
  },
  "4431695": {
    "espn_name": "Drew Timme",
    "rotowire_slug": "drew-timme-5916",
    "rotowire_id": "5916"
  },
  "4431699": {
    "espn_name": "Kai Jones",
    "rotowire_slug": "kai-jones-5386",
    "rotowire_id": "5386"
  },
  "4431705": {
    "espn_name": "Anton Watson",
    "rotowire_slug": "anton-watson-6037",
    "rotowire_id": "6037"
  },
  "4431714": {
    "espn_name": "Jalen Wilson",
    "rotowire_slug": "jalen-wilson-5926",
    "rotowire_id": "5926"
  },
  "4431720": {
    "espn_name": "Lester Quinones",
    "rotowire_slug": "lester-quinones-5669",
    "rotowire_id": "5669"
  },
  "4431727": {
    "espn_name": "Isaiah Wong",
    "rotowire_slug": "isaiah-wong-6038",
    "rotowire_id": "6038"
  },
  "4431736": {
    "espn_name": "Toumani Camara",
    "rotowire_slug": "toumani-camara-5987",
    "rotowire_id": "5987"
  },
  "4431752": {
    "espn_name": "Kobe Brown",
    "rotowire_slug": "kobe-brown-5957",
    "rotowire_id": "5957"
  },
  "4431766": {
    "espn_name": "Damion Baugh",
    "rotowire_slug": "damion-baugh-5948",
    "rotowire_id": "5948"
  },
  "4431767": {
    "espn_name": "Christian Braun",
    "rotowire_slug": "christian-braun-5710",
    "rotowire_id": "5710"
  },
  "4431772": {
    "espn_name": "Myron Gardner",
    "rotowire_slug": "myron-gardner-6067",
    "rotowire_id": "6067"
  },
  "4431775": {
    "espn_name": "Seth Lundy",
    "rotowire_slug": "seth-lundy-6003",
    "rotowire_id": "6003"
  },
  "4431778": {
    "espn_name": "Christian Koloko",
    "rotowire_slug": "christian-koloko-5645",
    "rotowire_id": "5645"
  },
  "4431785": {
    "espn_name": "Scotty Pippen Jr.",
    "rotowire_slug": "scotty-pippen-5685",
    "rotowire_id": "5685"
  },
  "4431786": {
    "espn_name": "Keshad Johnson",
    "rotowire_slug": "keshad-johnson-6285",
    "rotowire_id": "6285"
  },
  "4431811": {
    "espn_name": "Dereon Seabron",
    "rotowire_slug": "dereon-seabron-5730",
    "rotowire_id": "5730"
  },
  "4431816": {
    "espn_name": "Jesse Edwards",
    "rotowire_slug": "jesse-edwards-6306",
    "rotowire_id": "6306"
  },
  "4431823": {
    "espn_name": "Miles McBride",
    "rotowire_slug": "miles-mcbride-5402",
    "rotowire_id": "5402"
  },
  "4431828": {
    "espn_name": "KJ Martin",
    "rotowire_slug": "kj-martin-5116",
    "rotowire_id": "5116"
  },
  "4431893": {
    "espn_name": "Jamison Battle",
    "rotowire_slug": "jamison-battle-6323",
    "rotowire_id": "6323"
  },
  "4431941": {
    "espn_name": "RayJ Dennis",
    "rotowire_slug": "rayj-dennis-6378",
    "rotowire_id": "6378"
  },
  "4432070": {
    "espn_name": "Quincy Olivari",
    "rotowire_slug": "quincy-olivari-6348",
    "rotowire_id": "6348"
  },
  "4432107": {
    "espn_name": "Marcus Sasser",
    "rotowire_slug": "marcus-sasser-5962",
    "rotowire_id": "5962"
  },
  "4432117": {
    "espn_name": "Isaiah Stevens",
    "rotowire_slug": "isaiah-stevens-6035",
    "rotowire_id": "6035"
  },
  "4432158": {
    "espn_name": "Evan Mobley",
    "rotowire_slug": "evan-mobley-5355",
    "rotowire_id": "5355"
  },
  "4432162": {
    "espn_name": "Brandon Boston",
    "rotowire_slug": "brandon-boston-5406",
    "rotowire_id": "5406"
  },
  "4432164": {
    "espn_name": "Jaden Springer",
    "rotowire_slug": "jaden-springer-5407",
    "rotowire_id": "5407"
  },
  "4432165": {
    "espn_name": "Jalen Suggs",
    "rotowire_slug": "jalen-suggs-5379",
    "rotowire_id": "5379"
  },
  "4432166": {
    "espn_name": "Cade Cunningham",
    "rotowire_slug": "cade-cunningham-5336",
    "rotowire_id": "5336"
  },
  "4432168": {
    "espn_name": "Josh Christopher",
    "rotowire_slug": "josh-christopher-5335",
    "rotowire_id": "5335"
  },
  "4432170": {
    "espn_name": "Isaiah Jackson",
    "rotowire_slug": "isaiah-jackson-5403",
    "rotowire_id": "5403"
  },
  "4432171": {
    "espn_name": "Moses Moody",
    "rotowire_slug": "moses-moody-5384",
    "rotowire_id": "5384"
  },
  "4432173": {
    "espn_name": "Sharife Cooper",
    "rotowire_slug": "sharife-cooper-5388",
    "rotowire_id": "5388"
  },
  "4432174": {
    "espn_name": "Cam Thomas",
    "rotowire_slug": "cam-thomas-5360",
    "rotowire_id": "5360"
  },
  "4432176": {
    "espn_name": "Daishen Nix",
    "rotowire_slug": "daishen-nix-5259",
    "rotowire_id": "5259"
  },
  "4432179": {
    "espn_name": "MarJon Beauchamp",
    "rotowire_slug": "marjon-beauchamp-5564",
    "rotowire_id": "5564"
  },
  "4432180": {
    "espn_name": "Hunter Dickinson",
    "rotowire_slug": "hunter-dickinson-6667",
    "rotowire_id": "6667"
  },
  "4432181": {
    "espn_name": "Julian Strawther",
    "rotowire_slug": "julian-strawther-5915",
    "rotowire_id": "5915"
  },
  "4432185": {
    "espn_name": "Micah Peavy",
    "rotowire_slug": "micah-peavy-6607",
    "rotowire_id": "6607"
  },
  "4432187": {
    "espn_name": "Reece Beekman",
    "rotowire_slug": "reece-beekman-6292",
    "rotowire_id": "6292"
  },
  "4432190": {
    "espn_name": "Andre Jackson Jr.",
    "rotowire_slug": "andre-jackson-5947",
    "rotowire_id": "5947"
  },
  "4432192": {
    "espn_name": "Keon Johnson",
    "rotowire_slug": "keon-johnson-5340",
    "rotowire_id": "5340"
  },
  "4432194": {
    "espn_name": "Day'Ron Sharpe",
    "rotowire_slug": "dayron-sharpe-5418",
    "rotowire_id": "5418"
  },
  "4432241": {
    "espn_name": "Jamal Shead",
    "rotowire_slug": "jamal-shead-6296",
    "rotowire_id": "6296"
  },
  "4432247": {
    "espn_name": "Jaylen Clark",
    "rotowire_slug": "jaylen-clark-5972",
    "rotowire_id": "5972"
  },
  "4432356": {
    "espn_name": "Johnny Davis",
    "rotowire_slug": "johnny-davis-5637",
    "rotowire_id": "5637"
  },
  "4432446": {
    "espn_name": "Jabari Walker",
    "rotowire_slug": "jabari-walker-5675",
    "rotowire_id": "5675"
  },
  "4432573": {
    "espn_name": "Paolo Banchero",
    "rotowire_slug": "paolo-banchero-5700",
    "rotowire_id": "5700"
  },
  "4432582": {
    "espn_name": "Max Christie",
    "rotowire_slug": "max-christie-5723",
    "rotowire_id": "5723"
  },
  "4432588": {
    "espn_name": "John Butler Jr.",
    "rotowire_slug": "john-butler-5712",
    "rotowire_id": "5712"
  },
  "4432639": {
    "espn_name": "Jabari Smith Jr.",
    "rotowire_slug": "jabari-smith-5643",
    "rotowire_id": "5643"
  },
  "4432645": {
    "espn_name": "Trevor Keels",
    "rotowire_slug": "trevor-keels-5714",
    "rotowire_id": "5714"
  },
  "4432646": {
    "espn_name": "Kennedy Chandler",
    "rotowire_slug": "kennedy-chandler-5720",
    "rotowire_id": "5720"
  },
  "4432735": {
    "espn_name": "Dariq Whitehead",
    "rotowire_slug": "dariq-whitehead-5905",
    "rotowire_id": "5905"
  },
  "4432808": {
    "espn_name": "James Wiseman",
    "rotowire_slug": "james-wiseman-5100",
    "rotowire_id": "5100"
  },
  "4432809": {
    "espn_name": "Cole Anthony",
    "rotowire_slug": "cole-anthony-5232",
    "rotowire_id": "5232"
  },
  "4432810": {
    "espn_name": "Isaiah Stewart",
    "rotowire_slug": "isaiah-stewart-5137",
    "rotowire_id": "5137"
  },
  "4432811": {
    "espn_name": "Josh Green",
    "rotowire_slug": "josh-green-5192",
    "rotowire_id": "5192"
  },
  "4432813": {
    "espn_name": "Jeremiah Robinson-Earl",
    "rotowire_slug": "jeremiah-robinson-earl-5411",
    "rotowire_id": "5411"
  },
  "4432815": {
    "espn_name": "Isaiah Mobley",
    "rotowire_slug": "isaiah-mobley-5639",
    "rotowire_id": "5639"
  },
  "4432816": {
    "espn_name": "LaMelo Ball",
    "rotowire_slug": "lamelo-ball-5151",
    "rotowire_id": "5151"
  },
  "4432817": {
    "espn_name": "Johnny Juzang",
    "rotowire_slug": "johnny-juzang-5743",
    "rotowire_id": "5743"
  },
  "4432819": {
    "espn_name": "Tre Mann",
    "rotowire_slug": "tre-mann-5331",
    "rotowire_id": "5331"
  },
  "4432820": {
    "espn_name": "D.J. Carton",
    "rotowire_slug": "dj-carton-5442",
    "rotowire_id": "5442"
  },
  "4432821": {
    "espn_name": "E.J. Liddell",
    "rotowire_slug": "ej-liddell-5705",
    "rotowire_id": "5705"
  },
  "4432822": {
    "espn_name": "Isaac Okoro",
    "rotowire_slug": "isaac-okoro-5264",
    "rotowire_id": "5264"
  },
  "4432823": {
    "espn_name": "Jaylin Williams",
    "rotowire_slug": "jaylin-williams-6321",
    "rotowire_id": "6321"
  },
  "4432827": {
    "espn_name": "Oscar Tshiebwe",
    "rotowire_slug": "oscar-tshiebwe-5940",
    "rotowire_id": "5940"
  },
  "4432847": {
    "espn_name": "Terrence Shannon Jr.",
    "rotowire_slug": "terrence-shannon-6278",
    "rotowire_id": "6278"
  },
  "4432848": {
    "espn_name": "Jaime Jaquez Jr.",
    "rotowire_slug": "jaime-jaquez-5960",
    "rotowire_id": "5960"
  },
  "4432872": {
    "espn_name": "Emanuel Miller",
    "rotowire_slug": "emanuel-miller-6017",
    "rotowire_id": "6017"
  },
  "4432887": {
    "espn_name": "Tyson Etienne",
    "rotowire_slug": "tyson-etienne-5758",
    "rotowire_id": "5758"
  },
  "4432907": {
    "espn_name": "Justin Champagnie",
    "rotowire_slug": "justin-champagnie-5371",
    "rotowire_id": "5371"
  },
  "4432946": {
    "espn_name": "Jalen Bridges",
    "rotowire_slug": "jalen-bridges-6290",
    "rotowire_id": "6290"
  },
  "4432957": {
    "espn_name": "Yuri Collins",
    "rotowire_slug": "yuri-collins-6047",
    "rotowire_id": "6047"
  },
  "4432971": {
    "espn_name": "Alex Ducas",
    "rotowire_slug": "alex-ducas-6325",
    "rotowire_id": "6325"
  },
  "4433076": {
    "espn_name": "Ben Sheppard",
    "rotowire_slug": "ben-sheppard-6033",
    "rotowire_id": "6033"
  },
  "4433083": {
    "espn_name": "Cam Spencer",
    "rotowire_slug": "cam-spencer-6297",
    "rotowire_id": "6297"
  },
  "4433133": {
    "espn_name": "Jahmir Young",
    "rotowire_slug": "jahmir-young-6377",
    "rotowire_id": "6377"
  },
  "4433134": {
    "espn_name": "Scottie Barnes",
    "rotowire_slug": "scottie-barnes-5390",
    "rotowire_id": "5390"
  },
  "4433136": {
    "espn_name": "Walker Kessler",
    "rotowire_slug": "walker-kessler-5644",
    "rotowire_id": "5644"
  },
  "4433137": {
    "espn_name": "Ziaire Williams",
    "rotowire_slug": "ziaire-williams-5400",
    "rotowire_id": "5400"
  },
  "4433144": {
    "espn_name": "Caleb Love",
    "rotowire_slug": "caleb-love-6603",
    "rotowire_id": "6603"
  },
  "4433147": {
    "espn_name": "Marcus Bagley",
    "rotowire_slug": "marcus-bagley-5970",
    "rotowire_id": "5970"
  },
  "4433159": {
    "espn_name": "Dalen Terry",
    "rotowire_slug": "dalen-terry-5724",
    "rotowire_id": "5724"
  },
  "4433174": {
    "espn_name": "Dylan Cardwell",
    "rotowire_slug": "dylan-cardwell-6638",
    "rotowire_id": "6638"
  },
  "4433188": {
    "espn_name": "Devin Carter",
    "rotowire_slug": "devin-carter-6265",
    "rotowire_id": "6265"
  },
  "4433192": {
    "espn_name": "Tari Eason",
    "rotowire_slug": "tari-eason-5704",
    "rotowire_id": "5704"
  },
  "4433218": {
    "espn_name": "Jaden Ivey",
    "rotowire_slug": "jaden-ivey-5696",
    "rotowire_id": "5696"
  },
  "4433225": {
    "espn_name": "Tyler Kolek",
    "rotowire_slug": "tyler-kolek-6273",
    "rotowire_id": "6273"
  },
  "4433246": {
    "espn_name": "Patrick Baldwin Jr.",
    "rotowire_slug": "patrick-baldwin-5721",
    "rotowire_id": "5721"
  },
  "4433247": {
    "espn_name": "Jonathan Kuminga",
    "rotowire_slug": "jonathan-kuminga-5287",
    "rotowire_id": "5287"
  },
  "4433249": {
    "espn_name": "Moussa Diabate",
    "rotowire_slug": "moussa-diabate-5708",
    "rotowire_id": "5708"
  },
  "4433254": {
    "espn_name": "Kendall Brown",
    "rotowire_slug": "kendall-brown-5716",
    "rotowire_id": "5716"
  },
  "4433255": {
    "espn_name": "Chet Holmgren",
    "rotowire_slug": "chet-holmgren-5697",
    "rotowire_id": "5697"
  },
  "4433268": {
    "espn_name": "Trey Alexander",
    "rotowire_slug": "trey-alexander-6291",
    "rotowire_id": "6291"
  },
  "4433281": {
    "espn_name": "Hunter Sallis",
    "rotowire_slug": "hunter-sallis-6595",
    "rotowire_id": "6595"
  },
  "4433287": {
    "espn_name": "Brandon Miller",
    "rotowire_slug": "brandon-miller-5896",
    "rotowire_id": "5896"
  },
  "4433378": {
    "espn_name": "Colby Jones",
    "rotowire_slug": "colby-jones-5913",
    "rotowire_id": "5913"
  },
  "4433569": {
    "espn_name": "Johni Broome",
    "rotowire_slug": "johni-broome-6566",
    "rotowire_id": "6566"
  },
  "4433607": {
    "espn_name": "DaRon Holmes II",
    "rotowire_slug": "daron-holmes-6288",
    "rotowire_id": "6288"
  },
  "4433618": {
    "espn_name": "Harrison Ingram",
    "rotowire_slug": "harrison-ingram-6252",
    "rotowire_id": "6252"
  },
  "4433620": {
    "espn_name": "Emoni Bates",
    "rotowire_slug": "emoni-bates-5922",
    "rotowire_id": "5922"
  },
  "4433621": {
    "espn_name": "Jalen Duren",
    "rotowire_slug": "jalen-duren-5703",
    "rotowire_id": "5703"
  },
  "4433622": {
    "espn_name": "Chris Livingston",
    "rotowire_slug": "chris-livingston-5977",
    "rotowire_id": "5977"
  },
  "4433623": {
    "espn_name": "Caleb Houstan",
    "rotowire_slug": "caleb-houstan-5718",
    "rotowire_id": "5718"
  },
  "4433626": {
    "espn_name": "Jalen Hood-Schifino",
    "rotowire_slug": "jalen-hood-schifino-5897",
    "rotowire_id": "5897"
  },
  "4433627": {
    "espn_name": "Keyonte George",
    "rotowire_slug": "keyonte-george-5899",
    "rotowire_id": "5899"
  },
  "4433629": {
    "espn_name": "Ryan Nembhard",
    "rotowire_slug": "ryan-nembhard-6614",
    "rotowire_id": "6614"
  },
  "4437244": {
    "espn_name": "Jalen Green",
    "rotowire_slug": "jalen-green-5230",
    "rotowire_id": "5230"
  },
  "4438552": {
    "espn_name": "Onuralp Bitim",
    "rotowire_slug": "onuralp-bitim-6162",
    "rotowire_id": "6162"
  },
  "4565201": {
    "espn_name": "Malaki Branham",
    "rotowire_slug": "malaki-branham-5664",
    "rotowire_id": "5664"
  },
  "4566434": {
    "espn_name": "Franz Wagner",
    "rotowire_slug": "franz-wagner-5370",
    "rotowire_id": "5370"
  },
  "4576060": {
    "espn_name": "Ryan Kalkbrenner",
    "rotowire_slug": "ryan-kalkbrenner-6567",
    "rotowire_id": "6567"
  },
  "4576085": {
    "espn_name": "JD Davison",
    "rotowire_slug": "jd-davison-5642",
    "rotowire_id": "5642"
  },
  "4576086": {
    "espn_name": "Bryce McGowens",
    "rotowire_slug": "bryce-mcgowens-5719",
    "rotowire_id": "5719"
  },
  "4576087": {
    "espn_name": "Peyton Watson",
    "rotowire_slug": "peyton-watson-5722",
    "rotowire_id": "5722"
  },
  "4578893": {
    "espn_name": "Vit Krejci",
    "rotowire_slug": "vit-krejci-5233",
    "rotowire_id": "5233"
  },
  "4585610": {
    "espn_name": "Kenneth Lofton Jr.",
    "rotowire_slug": "kenneth-lofton-5727",
    "rotowire_id": "5727"
  },
  "4591259": {
    "espn_name": "Koby Brea",
    "rotowire_slug": "koby-brea-6572",
    "rotowire_id": "6572"
  },
  "4591725": {
    "espn_name": "Ryan Rollins",
    "rotowire_slug": "ryan-rollins-5668",
    "rotowire_id": "5668"
  },
  "4592187": {
    "espn_name": "Wendell Moore Jr.",
    "rotowire_slug": "wendell-moore-5715",
    "rotowire_id": "5715"
  },
  "4592216": {
    "espn_name": "Alondes Williams",
    "rotowire_slug": "alondes-williams-5674",
    "rotowire_id": "5674"
  },
  "4592401": {
    "espn_name": "N'Faly Dante",
    "rotowire_slug": "nfaly-dante-6302",
    "rotowire_id": "6302"
  },
  "4592402": {
    "espn_name": "Chris Duarte",
    "rotowire_slug": "chris-duarte-5345",
    "rotowire_id": "5345"
  },
  "4592427": {
    "espn_name": "Spencer Jones",
    "rotowire_slug": "spencer-jones-6315",
    "rotowire_id": "6315"
  },
  "4592435": {
    "espn_name": "Branden Carlson",
    "rotowire_slug": "branden-carlson-6326",
    "rotowire_id": "6326"
  },
  "4592461": {
    "espn_name": "Jacob Toppin",
    "rotowire_slug": "jacob-toppin-5902",
    "rotowire_id": "5902"
  },
  "4592479": {
    "espn_name": "Julian Champagnie",
    "rotowire_slug": "julian-champagnie-5728",
    "rotowire_id": "5728"
  },
  "4592492": {
    "espn_name": "Bones Hyland",
    "rotowire_slug": "bones-hyland-5397",
    "rotowire_id": "5397"
  },
  "4592686": {
    "espn_name": "Antonio Reeves",
    "rotowire_slug": "antonio-reeves-6028",
    "rotowire_id": "6028"
  },
  "4592691": {
    "espn_name": "Jake LaRavia",
    "rotowire_slug": "jake-laravia-5694",
    "rotowire_id": "5694"
  },
  "4592699": {
    "espn_name": "Enrique Freeman",
    "rotowire_slug": "enrique-freeman-6307",
    "rotowire_id": "6307"
  },
  "4592714": {
    "espn_name": "Pat Spencer",
    "rotowire_slug": "pat-spencer-5548",
    "rotowire_id": "5548"
  },
  "4592829": {
    "espn_name": "Quenton Jackson",
    "rotowire_slug": "quenton-jackson-5755",
    "rotowire_id": "5755"
  },
  "4592857": {
    "espn_name": "Isaiah Crawford",
    "rotowire_slug": "isaiah-crawford-6313",
    "rotowire_id": "6313"
  },
  "4592933": {
    "espn_name": "Mouhamadou Gueye",
    "rotowire_slug": "mouhamadou-gueye-5802",
    "rotowire_id": "5802"
  },
  "4592965": {
    "espn_name": "Tristen Newton",
    "rotowire_slug": "tristen-newton-6022",
    "rotowire_id": "6022"
  },
  "4592979": {
    "espn_name": "Zyon Pullin",
    "rotowire_slug": "zyon-pullin-6300",
    "rotowire_id": "6300"
  },
  "4593016": {
    "espn_name": "Quinten Post",
    "rotowire_slug": "quinten-post-6299",
    "rotowire_id": "6299"
  },
  "4593041": {
    "espn_name": "David Roddy",
    "rotowire_slug": "david-roddy-5713",
    "rotowire_id": "5713"
  },
  "4593049": {
    "espn_name": "Orlando Robinson",
    "rotowire_slug": "orlando-robinson-5779",
    "rotowire_id": "5779"
  },
  "4593125": {
    "espn_name": "Santi Aldama",
    "rotowire_slug": "santi-aldama-5428",
    "rotowire_id": "5428"
  },
  "4593803": {
    "espn_name": "Jalen Williams",
    "rotowire_slug": "jalen-williams-5687",
    "rotowire_id": "5687"
  },
  "4593841": {
    "espn_name": "Baylor Scheierman",
    "rotowire_slug": "baylor-scheierman-6280",
    "rotowire_id": "6280"
  },
  "4594268": {
    "espn_name": "Anthony Edwards",
    "rotowire_slug": "anthony-edwards-5110",
    "rotowire_id": "5110"
  },
  "4594326": {
    "espn_name": "Kris Murray",
    "rotowire_slug": "kris-murray-5943",
    "rotowire_id": "5943"
  },
  "4594327": {
    "espn_name": "Keegan Murray",
    "rotowire_slug": "keegan-murray-5699",
    "rotowire_id": "5699"
  },
  "4595400": {
    "espn_name": "Olivier-Maxence Prosper",
    "rotowire_slug": "olivier-maxence-prosper-5930",
    "rotowire_id": "5930"
  },
  "4597259": {
    "espn_name": "Javonte Cooke",
    "rotowire_slug": "javonte-cooke-5871",
    "rotowire_id": "5871"
  },
  "4597865": {
    "espn_name": "Tosan Evbuomwan",
    "rotowire_slug": "tosan-evbuomwan-5996",
    "rotowire_id": "5996"
  },
  "4598307": {
    "espn_name": "Dmytro Skapintsev",
    "rotowire_slug": "dmytro-skapintsev-5868",
    "rotowire_id": "5868"
  },
  "4600663": {
    "espn_name": "Zach Edey",
    "rotowire_slug": "zach-edey-6263",
    "rotowire_id": "6263"
  },
  "4601023": {
    "espn_name": "Oso Ighodaro",
    "rotowire_slug": "oso-ighodaro-6293",
    "rotowire_id": "6293"
  },
  "4601025": {
    "espn_name": "Pelle Larsson",
    "rotowire_slug": "pelle-larsson-6013",
    "rotowire_id": "6013"
  },
  "4602025": {
    "espn_name": "Sion James",
    "rotowire_slug": "sion-james-6582",
    "rotowire_id": "6582"
  },
  "4606840": {
    "espn_name": "Jamir Watkins",
    "rotowire_slug": "jamir-watkins-6573",
    "rotowire_id": "6573"
  },
  "4610139": {
    "espn_name": "Jeremy Sochan",
    "rotowire_slug": "jeremy-sochan-5702",
    "rotowire_id": "5702"
  },
  "4683021": {
    "espn_name": "Deni Avdija",
    "rotowire_slug": "deni-avdija-5152",
    "rotowire_id": "5152"
  },
  "4683023": {
    "espn_name": "Jay Scrubb",
    "rotowire_slug": "jay-scrubb-5117",
    "rotowire_id": "5117"
  },
  "4683024": {
    "espn_name": "Killian Hayes",
    "rotowire_slug": "killian-hayes-5121",
    "rotowire_id": "5121"
  },
  "4683634": {
    "espn_name": "Bennedict Mathurin",
    "rotowire_slug": "bennedict-mathurin-5698",
    "rotowire_id": "5698"
  },
  "4683678": {
    "espn_name": "Scoot Henderson",
    "rotowire_slug": "scoot-henderson-5377",
    "rotowire_id": "5377"
  },
  "4683686": {
    "espn_name": "Nick Smith Jr.",
    "rotowire_slug": "nick-smith-5909",
    "rotowire_id": "5909"
  },
  "4683688": {
    "espn_name": "Dereck Lively II",
    "rotowire_slug": "dereck-lively-5904",
    "rotowire_id": "5904"
  },
  "4683689": {
    "espn_name": "Jordan Walsh",
    "rotowire_slug": "jordan-walsh-5942",
    "rotowire_id": "5942"
  },
  "4683692": {
    "espn_name": "Cason Wallace",
    "rotowire_slug": "cason-wallace-5898",
    "rotowire_id": "5898"
  },
  "4683736": {
    "espn_name": "Kobe Bufkin",
    "rotowire_slug": "kobe-bufkin-5892",
    "rotowire_id": "5892"
  },
  "4683747": {
    "espn_name": "Jaylon Tyson",
    "rotowire_slug": "jaylon-tyson-6277",
    "rotowire_id": "6277"
  },
  "4683749": {
    "espn_name": "TyTy Washington Jr.",
    "rotowire_slug": "tyty-washington-5689",
    "rotowire_id": "5689"
  },
  "4683750": {
    "espn_name": "Jordan Hawkins",
    "rotowire_slug": "jordan-hawkins-5935",
    "rotowire_id": "5935"
  },
  "4683766": {
    "espn_name": "Isaiah Collier",
    "rotowire_slug": "isaiah-collier-6260",
    "rotowire_id": "6260"
  },
  "4683771": {
    "espn_name": "Ronald Holland II",
    "rotowire_slug": "ronald-holland-5939",
    "rotowire_id": "5939"
  },
  "4683774": {
    "espn_name": "Bronny James",
    "rotowire_slug": "bronny-james-6251",
    "rotowire_id": "6251"
  },
  "4683778": {
    "espn_name": "Jared McCain",
    "rotowire_slug": "jared-mccain-6266",
    "rotowire_id": "6266"
  },
  "4683834": {
    "espn_name": "KJ Simpson",
    "rotowire_slug": "kj-simpson-6286",
    "rotowire_id": "6286"
  },
  "4683934": {
    "espn_name": "Jahmai Mashack",
    "rotowire_slug": "jahmai-mashack-6647",
    "rotowire_id": "6647"
  },
  "4683935": {
    "espn_name": "Blake Wesley",
    "rotowire_slug": "blake-wesley-5652",
    "rotowire_id": "5652"
  },
  "4684208": {
    "espn_name": "Brooks Barnhizer",
    "rotowire_slug": "brooks-barnhizer-6633",
    "rotowire_id": "6633"
  },
  "4684272": {
    "espn_name": "Ja'Kobe Walter",
    "rotowire_slug": "jakobe-walter-6261",
    "rotowire_id": "6261"
  },
  "4684275": {
    "espn_name": "Rob Dillingham",
    "rotowire_slug": "rob-dillingham-6255",
    "rotowire_id": "6255"
  },
  "4684286": {
    "espn_name": "Maxwell Lewis",
    "rotowire_slug": "maxwell-lewis-5888",
    "rotowire_id": "5888"
  },
  "4684737": {
    "espn_name": "Jaylen Martin",
    "rotowire_slug": "jaylen-martin-6015",
    "rotowire_id": "6015"
  },
  "4684740": {
    "espn_name": "Amen Thompson",
    "rotowire_slug": "amen-thompson-5931",
    "rotowire_id": "5931"
  },
  "4684742": {
    "espn_name": "Ausar Thompson",
    "rotowire_slug": "ausar-thompson-5932",
    "rotowire_id": "5932"
  },
  "4684793": {
    "espn_name": "Kyle Filipowski",
    "rotowire_slug": "kyle-filipowski-6264",
    "rotowire_id": "6264"
  },
  "4684806": {
    "espn_name": "Taylor Hendricks",
    "rotowire_slug": "taylor-hendricks-5903",
    "rotowire_id": "5903"
  },
  "4687718": {
    "espn_name": "Josh Minott",
    "rotowire_slug": "josh-minott-5709",
    "rotowire_id": "5709"
  },
  "4696317": {
    "espn_name": "Miles Kelly",
    "rotowire_slug": "miles-kelly-6632",
    "rotowire_id": "6632"
  },
  "4700852": {
    "espn_name": "Chaz Lanier",
    "rotowire_slug": "chaz-lanier-6568",
    "rotowire_id": "6568"
  },
  "4701208": {
    "espn_name": "Moussa Cisse",
    "rotowire_slug": "moussa-cisse-6688",
    "rotowire_id": "6688"
  },
  "4701225": {
    "espn_name": "PJ Hall",
    "rotowire_slug": "pj-hall-6253",
    "rotowire_id": "6253"
  },
  "4701230": {
    "espn_name": "Jalen Johnson",
    "rotowire_slug": "jalen-johnson-6502",
    "rotowire_id": "6502"
  },
  "4701231": {
    "espn_name": "DJ Steward",
    "rotowire_slug": "dj-steward-5426",
    "rotowire_id": "5426"
  },
  "4701232": {
    "espn_name": "Mark Williams",
    "rotowire_slug": "mark-williams-5647",
    "rotowire_id": "5647"
  },
  "4701233": {
    "espn_name": "Craig Porter Jr.",
    "rotowire_slug": "craig-porter-6062",
    "rotowire_id": "6062"
  },
  "4701234": {
    "espn_name": "Ricky Council IV",
    "rotowire_slug": "ricky-council-5965",
    "rotowire_id": "5965"
  },
  "4702023": {
    "espn_name": "Adama Sanogo",
    "rotowire_slug": "adama-sanogo-5980",
    "rotowire_id": "5980"
  },
  "4702159": {
    "espn_name": "Dillon Jones",
    "rotowire_slug": "dillon-jones-6279",
    "rotowire_id": "6279"
  },
  "4702177": {
    "espn_name": "Keon Ellis",
    "rotowire_slug": "keon-ellis-5659",
    "rotowire_id": "5659"
  },
  "4702233": {
    "espn_name": "JT Thor",
    "rotowire_slug": "jt-thor-5413",
    "rotowire_id": "5413"
  },
  "4702352": {
    "espn_name": "Kobe Sanders",
    "rotowire_slug": "kobe-sanders-6619",
    "rotowire_id": "6619"
  },
  "4702382": {
    "espn_name": "Tristan da Silva",
    "rotowire_slug": "tristan-da-silva-6267",
    "rotowire_id": "6267"
  },
  "4702384": {
    "espn_name": "Nique Clifford",
    "rotowire_slug": "nique-clifford-6547",
    "rotowire_id": "6547"
  },
  "4702745": {
    "espn_name": "Amari Williams",
    "rotowire_slug": "amari-williams-6606",
    "rotowire_id": "6606"
  },
  "4702785": {
    "espn_name": "Jahmyl Telfort",
    "rotowire_slug": "jahmyl-telfort-6669",
    "rotowire_id": "6669"
  },
  "4702972": {
    "espn_name": "Chris Manon",
    "rotowire_slug": "chris-manon-6714",
    "rotowire_id": "6714"
  },
  "4703421": {
    "espn_name": "Taelon Peter",
    "rotowire_slug": "taelon-peter-6671",
    "rotowire_id": "6671"
  },
  "4703530": {
    "espn_name": "Mark Sears",
    "rotowire_slug": "mark-sears-6602",
    "rotowire_id": "6602"
  },
  "4706557": {
    "espn_name": "Chris Youngblood",
    "rotowire_slug": "chris-youngblood-6663",
    "rotowire_id": "6663"
  },
  "4708972": {
    "espn_name": "Jazian Gortman",
    "rotowire_slug": "jazian-gortman-5975",
    "rotowire_id": "5975"
  },
  "4709138": {
    "espn_name": "Brandin Podziemski",
    "rotowire_slug": "brandin-podziemski-5889",
    "rotowire_id": "5889"
  },
  "4711272": {
    "espn_name": "Reed Sheppard",
    "rotowire_slug": "reed-sheppard-6257",
    "rotowire_id": "6257"
  },
  "4711294": {
    "espn_name": "Matas Buzelis",
    "rotowire_slug": "matas-buzelis-5938",
    "rotowire_id": "5938"
  },
  "4711297": {
    "espn_name": "Justin Edwards",
    "rotowire_slug": "justin-edwards-6274",
    "rotowire_id": "6274"
  },
  "4712849": {
    "espn_name": "Anthony Black",
    "rotowire_slug": "anthony-black-5910",
    "rotowire_id": "5910"
  },
  "4712863": {
    "espn_name": "Mouhamed Gueye",
    "rotowire_slug": "mouhamed-gueye-5968",
    "rotowire_id": "5968"
  },
  "4712896": {
    "espn_name": "Noah Clowney",
    "rotowire_slug": "noah-clowney-5901",
    "rotowire_id": "5901"
  },
  "4713010": {
    "espn_name": "David Jones Garcia",
    "rotowire_slug": "david-jones-garcia-6309",
    "rotowire_id": "6309"
  },
  "4781746": {
    "espn_name": "Javon Small",
    "rotowire_slug": "javon-small-6581",
    "rotowire_id": "6581"
  },
  "4845363": {
    "espn_name": "Cam Christie",
    "rotowire_slug": "cam-christie-6283",
    "rotowire_id": "6283"
  },
  "4845367": {
    "espn_name": "Stephon Castle",
    "rotowire_slug": "stephon-castle-6250",
    "rotowire_id": "6250"
  },
  "4845374": {
    "espn_name": "Bub Carrington",
    "rotowire_slug": "bub-carrington-6270",
    "rotowire_id": "6270"
  },
  "4868423": {
    "espn_name": "Jaden Hardy",
    "rotowire_slug": "jaden-hardy-5374",
    "rotowire_id": "5374"
  },
  "4869342": {
    "espn_name": "Dyson Daniels",
    "rotowire_slug": "dyson-daniels-5385",
    "rotowire_id": "5385"
  },
  "4869780": {
    "espn_name": "Derik Queen",
    "rotowire_slug": "derik-queen-6541",
    "rotowire_id": "6541"
  },
  "4870562": {
    "espn_name": "Dominick Barlow",
    "rotowire_slug": "dominick-barlow-5670",
    "rotowire_id": "5670"
  },
  "4871140": {
    "espn_name": "Ibou Badji",
    "rotowire_slug": "ibou-badji-5782",
    "rotowire_id": "5782"
  },
  "4871141": {
    "espn_name": "Ariel Hukporti",
    "rotowire_slug": "ariel-hukporti-5778",
    "rotowire_id": "5778"
  },
  "4871144": {
    "espn_name": "Alperen Sengun",
    "rotowire_slug": "alperen-sengun-5404",
    "rotowire_id": "5404"
  },
  "4871145": {
    "espn_name": "Josh Giddey",
    "rotowire_slug": "josh-giddey-5366",
    "rotowire_id": "5366"
  },
  "4873138": {
    "espn_name": "Ace Bailey",
    "rotowire_slug": "ace-bailey-6551",
    "rotowire_id": "6551"
  },
  "4873201": {
    "espn_name": "Asa Newell",
    "rotowire_slug": "asa-newell-6561",
    "rotowire_id": "6561"
  },
  "4888725": {
    "espn_name": "Ryan Dunn",
    "rotowire_slug": "ryan-dunn-6276",
    "rotowire_id": "6276"
  },
  "4895758": {
    "espn_name": "Cody Williams",
    "rotowire_slug": "cody-williams-6259",
    "rotowire_id": "6259"
  },
  "4896372": {
    "espn_name": "Walter Clayton Jr.",
    "rotowire_slug": "walter-clayton-6575",
    "rotowire_id": "6575"
  },
  "4896850": {
    "espn_name": "Taran Armstrong",
    "rotowire_slug": "taran-armstrong-6539",
    "rotowire_id": "6539"
  },
  "4897262": {
    "espn_name": "Will Richard",
    "rotowire_slug": "will-richard-6625",
    "rotowire_id": "6625"
  },
  "4897449": {
    "espn_name": "Malevy Leons",
    "rotowire_slug": "malevy-leons-6329",
    "rotowire_id": "6329"
  },
  "4897943": {
    "espn_name": "Dalton Knecht",
    "rotowire_slug": "dalton-knecht-6258",
    "rotowire_id": "6258"
  },
  "4898369": {
    "espn_name": "Curtis Jones",
    "rotowire_slug": "curtis-jones-6627",
    "rotowire_id": "6627"
  },
  "4898371": {
    "espn_name": "Maxime Raynaud",
    "rotowire_slug": "maxime-raynaud-6552",
    "rotowire_id": "6552"
  },
  "4900671": {
    "espn_name": "Ajay Mitchell",
    "rotowire_slug": "ajay-mitchell-6289",
    "rotowire_id": "6289"
  },
  "4903027": {
    "espn_name": "Cedric Coward",
    "rotowire_slug": "cedric-coward-6592",
    "rotowire_id": "6592"
  },
  "4906923": {
    "espn_name": "Bobi Klintman",
    "rotowire_slug": "bobi-klintman-5976",
    "rotowire_id": "5976"
  },
  "4909710": {
    "espn_name": "Phillip Wheeler",
    "rotowire_slug": "phillip-wheeler-5574",
    "rotowire_id": "5574"
  },
  "4914336": {
    "espn_name": "Shaedon Sharpe",
    "rotowire_slug": "shaedon-sharpe-5693",
    "rotowire_id": "5693"
  },
  "4997526": {
    "espn_name": "Ousmane Dieng",
    "rotowire_slug": "ousmane-dieng-5695",
    "rotowire_id": "5695"
  },
  "4997528": {
    "espn_name": "Nikola Jovic",
    "rotowire_slug": "nikola-jovic-5640",
    "rotowire_id": "5640"
  },
  "4997536": {
    "espn_name": "Gui Santos",
    "rotowire_slug": "gui-santos-5738",
    "rotowire_id": "5738"
  },
  "4997537": {
    "espn_name": "Tristan Vukcevic",
    "rotowire_slug": "tristan-vukcevic-6000",
    "rotowire_id": "6000"
  },
  "4997538": {
    "espn_name": "Karlo Matkovic",
    "rotowire_slug": "karlo-matkovic-5737",
    "rotowire_id": "5737"
  },
  "4997539": {
    "espn_name": "Luke Travers",
    "rotowire_slug": "luke-travers-5739",
    "rotowire_id": "5739"
  },
  "5023693": {
    "espn_name": "Tyrese Proctor",
    "rotowire_slug": "tyrese-proctor-6569",
    "rotowire_id": "6569"
  },
  "5037871": {
    "espn_name": "Dylan Harper",
    "rotowire_slug": "dylan-harper-6549",
    "rotowire_id": "6549"
  },
  "5037873": {
    "espn_name": "Drake Powell",
    "rotowire_slug": "drake-powell-6610",
    "rotowire_id": "6610"
  },
  "5041939": {
    "espn_name": "Cooper Flagg",
    "rotowire_slug": "cooper-flagg-6548",
    "rotowire_id": "6548"
  },
  "5044385": {
    "espn_name": "Leonard Miller",
    "rotowire_slug": "leonard-miller-5804",
    "rotowire_id": "5804"
  },
  "5060631": {
    "espn_name": "Adou Thiero",
    "rotowire_slug": "adou-thiero-6578",
    "rotowire_id": "6578"
  },
  "5061568": {
    "espn_name": "Carter Bryant",
    "rotowire_slug": "carter-bryant-6556",
    "rotowire_id": "6556"
  },
  "5061575": {
    "espn_name": "Kon Knueppel",
    "rotowire_slug": "kon-knueppel-6540",
    "rotowire_id": "6540"
  },
  "5061589": {
    "espn_name": "Yves Missi",
    "rotowire_slug": "yves-missi-6268",
    "rotowire_id": "6268"
  },
  "5081727": {
    "espn_name": "Sidy Cissoko",
    "rotowire_slug": "sidy-cissoko-5799",
    "rotowire_id": "5799"
  },
  "5091709": {
    "espn_name": "Lachlan Olbrich",
    "rotowire_slug": "lachlan-olbrich-6618",
    "rotowire_id": "6618"
  },
  "5093267": {
    "espn_name": "Collin Murray-Boyles",
    "rotowire_slug": "collin-murray-boyles-6585",
    "rotowire_id": "6585"
  },
  "5099752": {
    "espn_name": "Rayan Rupert",
    "rotowire_slug": "rayan-rupert-5936",
    "rotowire_id": "5936"
  },
  "5104155": {
    "espn_name": "Bilal Coulibaly",
    "rotowire_slug": "bilal-coulibaly-5945",
    "rotowire_id": "5945"
  },
  "5104156": {
    "espn_name": "Armel Traore",
    "rotowire_slug": "armel-traore-6312",
    "rotowire_id": "6312"
  },
  "5104157": {
    "espn_name": "Victor Wembanyama",
    "rotowire_slug": "victor-wembanyama-5809",
    "rotowire_id": "5809"
  },
  "5105550": {
    "espn_name": "GG Jackson",
    "rotowire_slug": "gg-jackson-5946",
    "rotowire_id": "5946"
  },
  "5105553": {
    "espn_name": "Julian Phillips",
    "rotowire_slug": "julian-phillips-5978",
    "rotowire_id": "5978"
  },
  "5105565": {
    "espn_name": "Donovan Clingan",
    "rotowire_slug": "donovan-clingan-6254",
    "rotowire_id": "6254"
  },
  "5105592": {
    "espn_name": "Cam Whitmore",
    "rotowire_slug": "cam-whitmore-5934",
    "rotowire_id": "5934"
  },
  "5105623": {
    "espn_name": "Kel'el Ware",
    "rotowire_slug": "kelel-ware-6275",
    "rotowire_id": "6275"
  },
  "5105637": {
    "espn_name": "Adem Bona",
    "rotowire_slug": "adem-bona-6287",
    "rotowire_id": "6287"
  },
  "5105638": {
    "espn_name": "Amari Bailey",
    "rotowire_slug": "amari-bailey-5921",
    "rotowire_id": "5921"
  },
  "5105806": {
    "espn_name": "Jett Howard",
    "rotowire_slug": "jett-howard-5914",
    "rotowire_id": "5914"
  },
  "5105839": {
    "espn_name": "Brice Sensabaugh",
    "rotowire_slug": "brice-sensabaugh-5937",
    "rotowire_id": "5937"
  },
  "5105977": {
    "espn_name": "Rasheer Fleming",
    "rotowire_slug": "rasheer-fleming-6564",
    "rotowire_id": "6564"
  },
  "5106060": {
    "espn_name": "Jarace Walker",
    "rotowire_slug": "jarace-walker-5933",
    "rotowire_id": "5933"
  },
  "5106258": {
    "espn_name": "Gradey Dick",
    "rotowire_slug": "gradey-dick-5927",
    "rotowire_id": "5927"
  },
  "5106268": {
    "espn_name": "Nae'Qwan Tomlin",
    "rotowire_slug": "naeqwan-tomlin-6311",
    "rotowire_id": "6311"
  },
  "5107173": {
    "espn_name": "Danny Wolf",
    "rotowire_slug": "danny-wolf-6560",
    "rotowire_id": "6560"
  },
  "5107199": {
    "espn_name": "Daniss Jenkins",
    "rotowire_slug": "daniss-jenkins-6336",
    "rotowire_id": "6336"
  },
  "5107818": {
    "espn_name": "Isaac Jones",
    "rotowire_slug": "isaac-jones-6304",
    "rotowire_id": "6304"
  },
  "5107897": {
    "espn_name": "Jonathan Mogbo",
    "rotowire_slug": "jonathan-mogbo-6310",
    "rotowire_id": "6310"
  },
  "5108024": {
    "espn_name": "Yanic Konan Niederhauser",
    "rotowire_slug": "yanic-konan-niederhauser-6616",
    "rotowire_id": "6616"
  },
  "5112087": {
    "espn_name": "Jaylen Wells",
    "rotowire_slug": "jaylen-wells-6305",
    "rotowire_id": "6305"
  },
  "5124612": {
    "espn_name": "VJ Edgecombe",
    "rotowire_slug": "vj-edgecombe-6550",
    "rotowire_id": "6550"
  },
  "5144091": {
    "espn_name": "Jeremiah Fears",
    "rotowire_slug": "jeremiah-fears-6546",
    "rotowire_id": "6546"
  },
  "5144126": {
    "espn_name": "Will Riley",
    "rotowire_slug": "will-riley-6588",
    "rotowire_id": "6588"
  },
  "5157066": {
    "espn_name": "Johnny Furphy",
    "rotowire_slug": "johnny-furphy-6272",
    "rotowire_id": "6272"
  },
  "5159486": {
    "espn_name": "Yongxi Cui",
    "rotowire_slug": "yongxi-cui-6388",
    "rotowire_id": "6388"
  },
  "5159895": {
    "espn_name": "Yuki Kawamura",
    "rotowire_slug": "yuki-kawamura-6425",
    "rotowire_id": "6425"
  },
  "5160992": {
    "espn_name": "Alex Sarr",
    "rotowire_slug": "alex-sarr-6240",
    "rotowire_id": "6240"
  },
  "5165257": {
    "espn_name": "Trentyn Flowers",
    "rotowire_slug": "trentyn-flowers-6163",
    "rotowire_id": "6163"
  },
  "5167876": {
    "espn_name": "Tyler Smith",
    "rotowire_slug": "tyler-smith-5997",
    "rotowire_id": "5997"
  },
  "5170947": {
    "espn_name": "AJ Johnson",
    "rotowire_slug": "aj-johnson-6294",
    "rotowire_id": "6294"
  },
  "5174563": {
    "espn_name": "Kyshawn George",
    "rotowire_slug": "kyshawn-george-6269",
    "rotowire_id": "6269"
  },
  "5175643": {
    "espn_name": "Egor Demin",
    "rotowire_slug": "egor-demin-6559",
    "rotowire_id": "6559"
  },
  "5175647": {
    "espn_name": "Hugo Gonzalez",
    "rotowire_slug": "hugo-gonzalez-6553",
    "rotowire_id": "6553"
  },
  "5177362": {
    "espn_name": "Riley Minix",
    "rotowire_slug": "riley-minix-6314",
    "rotowire_id": "6314"
  },
  "5184018": {
    "espn_name": "Maozinha Pereira",
    "rotowire_slug": "maozinha-pereira-6215",
    "rotowire_id": "6215"
  },
  "5203685": {
    "espn_name": "Khaman Maluach",
    "rotowire_slug": "khaman-maluach-6542",
    "rotowire_id": "6542"
  },
  "5211175": {
    "espn_name": "Zaccharie Risacher",
    "rotowire_slug": "zaccharie-risacher-6249",
    "rotowire_id": "6249"
  },
  "5211176": {
    "espn_name": "Tidjane Salaun",
    "rotowire_slug": "tidjane-salaun-6262",
    "rotowire_id": "6262"
  },
  "5211983": {
    "espn_name": "Pacome Dadiet",
    "rotowire_slug": "pacome-dadiet-6281",
    "rotowire_id": "6281"
  },
  "5211984": {
    "espn_name": "Ulrich Chomche",
    "rotowire_slug": "ulrich-chomche-6284",
    "rotowire_id": "6284"
  },
  "5214637": {
    "espn_name": "Noah Penda",
    "rotowire_slug": "noah-penda-6577",
    "rotowire_id": "6577"
  },
  "5217746": {
    "espn_name": "Yang Hansen",
    "rotowire_slug": "yang-hansen-6617",
    "rotowire_id": "6617"
  },
  "5238230": {
    "espn_name": "Tre Johnson",
    "rotowire_slug": "tre-johnson-6543",
    "rotowire_id": "6543"
  },
  "5239561": {
    "espn_name": "Jase Richardson",
    "rotowire_slug": "jase-richardson-6545",
    "rotowire_id": "6545"
  },
  "5239590": {
    "espn_name": "Liam McNeeley",
    "rotowire_slug": "liam-mcneeley-6589",
    "rotowire_id": "6589"
  },
  "5242496": {
    "espn_name": "Noa Essengue",
    "rotowire_slug": "noa-essengue-6586",
    "rotowire_id": "6586"
  },
  "5242502": {
    "espn_name": "Ben Saraf",
    "rotowire_slug": "ben-saraf-6563",
    "rotowire_id": "6563"
  },
  "5279130": {
    "espn_name": "Nolan Traore",
    "rotowire_slug": "nolan-traore-6587",
    "rotowire_id": "6587"
  },
  "5279133": {
    "espn_name": "Joan Beringer",
    "rotowire_slug": "joan-beringer-6576",
    "rotowire_id": "6576"
  },
  "5289900": {
    "espn_name": "Mohamed Diawara",
    "rotowire_slug": "mohamed-diawara-6634",
    "rotowire_id": "6634"
  },
  "6427": {
    "espn_name": "Bismack Biyombo",
    "rotowire_slug": "bismack-biyombo-3191",
    "rotowire_id": "3191"
  },
  "6429": {
    "espn_name": "Alec Burks",
    "rotowire_slug": "alec-burks-3192",
    "rotowire_id": "3192"
  },
  "6430": {
    "espn_name": "Jimmy Butler III",
    "rotowire_slug": "jimmy-butler-3231",
    "rotowire_id": "3231"
  },
  "6440": {
    "espn_name": "Tobias Harris",
    "rotowire_slug": "tobias-harris-3211",
    "rotowire_id": "3211"
  },
  "6442": {
    "espn_name": "Kyrie Irving",
    "rotowire_slug": "kyrie-irving-3186",
    "rotowire_id": "3186"
  },
  "6443": {
    "espn_name": "Reggie Jackson",
    "rotowire_slug": "reggie-jackson-3217",
    "rotowire_id": "3217"
  },
  "6446": {
    "espn_name": "Cory Joseph",
    "rotowire_slug": "cory-joseph-3226",
    "rotowire_id": "3226"
  },
  "6450": {
    "espn_name": "Kawhi Leonard",
    "rotowire_slug": "kawhi-leonard-3195",
    "rotowire_id": "3195"
  },
  "6461": {
    "espn_name": "Markieff Morris",
    "rotowire_slug": "markieff-morris-3200",
    "rotowire_id": "3200"
  },
  "6474": {
    "espn_name": "Tristan Thompson",
    "rotowire_slug": "tristan-thompson-3196",
    "rotowire_id": "3196"
  },
  "6475": {
    "espn_name": "Klay Thompson",
    "rotowire_slug": "klay-thompson-3197",
    "rotowire_id": "3197"
  },
  "6477": {
    "espn_name": "Jonas Valanciunas",
    "rotowire_slug": "jonas-valanciunas-3190",
    "rotowire_id": "3190"
  },
  "6478": {
    "espn_name": "Nikola Vucevic",
    "rotowire_slug": "nikola-vucevic-3212",
    "rotowire_id": "3212"
  },
  "6578": {
    "espn_name": "Harrison Barnes",
    "rotowire_slug": "harrison-barnes-3305",
    "rotowire_id": "3305"
  },
  "6580": {
    "espn_name": "Bradley Beal",
    "rotowire_slug": "bradley-beal-3303",
    "rotowire_id": "3303"
  },
  "6581": {
    "espn_name": "Jae Crowder",
    "rotowire_slug": "jae-crowder-3324",
    "rotowire_id": "3324"
  },
  "6583": {
    "espn_name": "Anthony Davis",
    "rotowire_slug": "anthony-davis-3297",
    "rotowire_id": "3297"
  },
  "6585": {
    "espn_name": "Andre Drummond",
    "rotowire_slug": "andre-drummond-3300",
    "rotowire_id": "3300"
  },
  "6589": {
    "espn_name": "Draymond Green",
    "rotowire_slug": "draymond-green-3299",
    "rotowire_id": "3299"
  },
  "6606": {
    "espn_name": "Damian Lillard",
    "rotowire_slug": "damian-lillard-3304",
    "rotowire_id": "3304"
  },
  "6609": {
    "espn_name": "Khris Middleton",
    "rotowire_slug": "khris-middleton-3356",
    "rotowire_id": "3356"
  },
  "5144067": {
    "espn_name": "Nikola Durisic",
    "rotowire_slug": "nikola-durisic-5993",
    "rotowire_id": "5993"
  },
  "4697268": {
    "espn_name": "Kam Jones",
    "rotowire_slug": "kam-jones-6565",
    "rotowire_id": "6565"
  },
  "5214640": {
    "espn_name": "Kasparas Jakucionis",
    "rotowire_slug": "kasparas-jakucionis-6557",
    "rotowire_id": "6557"
  },
  "5170949": {
    "espn_name": "Alex Toohey",
    "rotowire_slug": "alex-toohey-6555",
    "rotowire_id": "6555"
  },
  "5159925": {
    "espn_name": "Nikola Topic",
    "rotowire_slug": "nikola-topic-6256",
    "rotowire_id": "6256"
  },
  "4683933": {
    "espn_name": "Tamar Bates",
    "rotowire_slug": "tamar-bates-6621",
    "rotowire_id": "6621"
  },
  "5160994": {
    "espn_name": "Sam Mennenga",
    "rotowire_slug": "sam-mennenga-6731",
    "rotowire_id": "6731"
  },
  "4396963": {
    "espn_name": "Blake Hinson",
    "rotowire_slug": "blake-hinson-6316",
    "rotowire_id": "6316"
  },
  "4397000": {
    "espn_name": "Tevian Jones",
    "rotowire_slug": "tevian-jones-6057",
    "rotowire_id": "6057"
  },
  "4397093": {
    "espn_name": "Warren Washington",
    "rotowire_slug": "warren-washington-6380",
    "rotowire_id": "6380"
  },
  "4397072": {
    "espn_name": "James Akinjo",
    "rotowire_slug": "james-akinjo-5813",
    "rotowire_id": "5813"
  },
  "4279920": {
    "espn_name": "Grayson Murphy",
    "rotowire_slug": "grayson-murphy-6396",
    "rotowire_id": "6396"
  },
  "4702602": {
    "espn_name": "CJ Huntley",
    "rotowire_slug": "cj-huntley-6672",
    "rotowire_id": "6672"
  },
  "4278373": {
    "espn_name": "Caleb Daniels",
    "rotowire_slug": "caleb-daniels-5919",
    "rotowire_id": "5919"
  },
  "5106035": {
    "espn_name": "RJ Luis Jr.",
    "rotowire_slug": "rj-luis-6611",
    "rotowire_id": "6611"
  },
  "4897197": {
    "espn_name": "Augustas Marciulionis",
    "rotowire_slug": "augustas-marciulionis-6675",
    "rotowire_id": "6675"
  },
  "4702670": {
    "espn_name": "Grant Nelson",
    "rotowire_slug": "grant-nelson-6298",
    "rotowire_id": "6298"
  },
  "5144071": {
    "espn_name": "Eli John Ndiaye",
    "rotowire_slug": "eli-john-ndiaye-6642",
    "rotowire_id": "6642"
  },
  "4593043": {
    "espn_name": "John Tonje",
    "rotowire_slug": "john-tonje-6570",
    "rotowire_id": "6570"
  },
  "4279924": {
    "espn_name": "Pedro Bradshaw",
    "rotowire_slug": "pedro-bradshaw-5525",
    "rotowire_id": "5525"
  },
  "4431674": {
    "espn_name": "Armando Bacot",
    "rotowire_slug": "armando-bacot-6339",
    "rotowire_id": "6339"
  },
  "3957103": {
    "espn_name": "Jordan Floyd",
    "rotowire_slug": "jordan-floyd-5464",
    "rotowire_id": "5464"
  },
  "5165268": {
    "espn_name": "Parker Jackson-Cartwright",
    "rotowire_slug": "parker-jackson-cartwright-4673",
    "rotowire_id": "4673"
  },
  "4423311": {
    "espn_name": "Yovel Zoosman",
    "rotowire_slug": "yovel-zoosman-4746",
    "rotowire_id": "4746"
  },
  "4701992": {
    "espn_name": "Max Shulga",
    "rotowire_slug": "max-shulga-6629",
    "rotowire_id": "6629"
  },
  "4898237": {
    "espn_name": "Bez Mbeng",
    "rotowire_slug": "bez-mbeng-6701",
    "rotowire_id": "6701"
  },
  "4596528": {
    "espn_name": "Lawson Lovering",
    "rotowire_slug": "lawson-lovering-6744",
    "rotowire_id": "6744"
  },
  "4278395": {
    "espn_name": "Taylor Funk",
    "rotowire_slug": "taylor-funk-6053",
    "rotowire_id": "6053"
  },
  "4700818": {
    "espn_name": "Vladislav Goldin",
    "rotowire_slug": "vladislav-goldin-6571",
    "rotowire_id": "6571"
  },
  "4397231": {
    "espn_name": "Miller Kopp",
    "rotowire_slug": "miller-kopp-6218",
    "rotowire_id": "6218"
  },
  "4431964": {
    "espn_name": "Max Fiedler",
    "rotowire_slug": "max-fiedler-6344",
    "rotowire_id": "6344"
  },
  "4078506": {
    "espn_name": "Austin Wiley",
    "rotowire_slug": "austin-wiley-5200",
    "rotowire_id": "5200"
  },
  "4433176": {
    "espn_name": "RJ Davis",
    "rotowire_slug": "rj-davis-6640",
    "rotowire_id": "6640"
  },
  "4593385": {
    "espn_name": "Aaron Estrada",
    "rotowire_slug": "aaron-estrada-6353",
    "rotowire_id": "6353"
  },
  "4406489": {
    "espn_name": "Adonis Arms",
    "rotowire_slug": "adonis-arms-5762",
    "rotowire_id": "5762"
  },
  "4431776": {
    "espn_name": "Jaylin Williams",
    "rotowire_slug": "jaylin-williams-6321",
    "rotowire_id": "6321"
  },
  "4398356": {
    "espn_name": "Gabe McGlothan",
    "rotowire_slug": "gabe-mcglothan-6352",
    "rotowire_id": "6352"
  },
  "4702099": {
    "espn_name": "Zack Austin",
    "rotowire_slug": "zack-austin-6692",
    "rotowire_id": "6692"
  },
  "4277844": {
    "espn_name": "Jordan Tucker",
    "rotowire_slug": "jordan-tucker-5275",
    "rotowire_id": "5275"
  },
  "4432068": {
    "espn_name": "Josh Oduro",
    "rotowire_slug": "josh-oduro-6349",
    "rotowire_id": "6349"
  },
  "4433183": {
    "espn_name": "Lamont Butler",
    "rotowire_slug": "lamont-butler-6641",
    "rotowire_id": "6641"
  },
  "5231917": {
    "espn_name": "Freddie Gillespie",
    "rotowire_slug": "freddie-gillespie-5257",
    "rotowire_id": "5257"
  },
  "4593106": {
    "espn_name": "Boogie Ellis",
    "rotowire_slug": "boogie-ellis-6319",
    "rotowire_id": "6319"
  },
  "4432103": {
    "espn_name": "DJ Rodman",
    "rotowire_slug": "dj-rodman-6434",
    "rotowire_id": "6434"
  },
  "4592712": {
    "espn_name": "Boo Buie",
    "rotowire_slug": "boo-buie-6343",
    "rotowire_id": "6343"
  },
  "4432394": {
    "espn_name": "Cameron Matthews",
    "rotowire_slug": "cameron-matthews-6670",
    "rotowire_id": "6670"
  },
  "4396657": {
    "espn_name": "Moses Wood",
    "rotowire_slug": "moses-wood-6370",
    "rotowire_id": "6370"
  },
  "4431914": {
    "espn_name": "Tyler Burton",
    "rotowire_slug": "tyler-burton-5986",
    "rotowire_id": "5986"
  },
  "4701845": {
    "espn_name": "Kadary Richmond",
    "rotowire_slug": "kadary-richmond-6639",
    "rotowire_id": "6639"
  },
  "4897696": {
    "espn_name": "Jamarion Sharp",
    "rotowire_slug": "jamarion-sharp-6376",
    "rotowire_id": "6376"
  },
  "4701228": {
    "espn_name": "Christian Shumate",
    "rotowire_slug": "christian-shumate-6777",
    "rotowire_id": "6777"
  },
  "4397450": {
    "espn_name": "Darius Brown",
    "rotowire_slug": "darius-brown-6367",
    "rotowire_id": "6367"
  },
  "4431718": {
    "espn_name": "Eric Dixon",
    "rotowire_slug": "eric-dixon-6584",
    "rotowire_id": "6584"
  },
  "4702656": {
    "espn_name": "Alijah Martin",
    "rotowire_slug": "alijah-martin-6612",
    "rotowire_id": "6612"
  },
  "4397101": {
    "espn_name": "Will Richardson",
    "rotowire_slug": "will-richardson-5925",
    "rotowire_id": "5925"
  },
  "4432753": {
    "espn_name": "Gabe Madsen",
    "rotowire_slug": "gabe-madsen-6637",
    "rotowire_id": "6637"
  },
  "4432188": {
    "espn_name": "Dawson Garcia",
    "rotowire_slug": "dawson-garcia-6631",
    "rotowire_id": "6631"
  },
  "4432189": {
    "espn_name": "Dain Dainja",
    "rotowire_slug": "dain-dainja-6703",
    "rotowire_id": "6703"
  },
  "4898238": {
    "espn_name": "John Poulakidas",
    "rotowire_slug": "john-poulakidas-6636",
    "rotowire_id": "6636"
  },
  "4431685": {
    "espn_name": "Josiah-Jordan James",
    "rotowire_slug": "josiah-jordan-james-6327",
    "rotowire_id": "6327"
  },
  "4593034": {
    "espn_name": "Alex Morales",
    "rotowire_slug": "alex-morales-5764",
    "rotowire_id": "5764"
  },
  "5157587": {
    "espn_name": "Rocco Zikarsky",
    "rotowire_slug": "rocco-zikarsky-6597",
    "rotowire_id": "6597"
  },
  "4684729": {
    "espn_name": "Judah Mintz",
    "rotowire_slug": "judah-mintz-6295",
    "rotowire_id": "6295"
  },
  "4397114": {
    "espn_name": "Cormac Ryan",
    "rotowire_slug": "cormac-ryan-6351",
    "rotowire_id": "6351"
  },
  "4897007": {
    "espn_name": "Matthew Cleveland",
    "rotowire_slug": "matthew-cleveland-6651",
    "rotowire_id": "6651"
  },
  "4683631": {
    "espn_name": "Daniel Batcho",
    "rotowire_slug": "daniel-batcho-6763",
    "rotowire_id": "6763"
  },
  "4592453": {
    "espn_name": "Sean East II",
    "rotowire_slug": "sean-east-6347",
    "rotowire_id": "6347"
  },
  "4565203": {
    "espn_name": "Charles Bediako",
    "rotowire_slug": "charles-bediako-5951",
    "rotowire_id": "5951"
  },
  "5174655": {
    "espn_name": "Chaney Johnson",
    "rotowire_slug": "chaney-johnson-6679",
    "rotowire_id": "6679"
  },
  "4280041": {
    "espn_name": "Javante McCoy",
    "rotowire_slug": "javante-mccoy-5678",
    "rotowire_id": "5678"
  },
  "4431734": {
    "espn_name": "Tristan Enaruna",
    "rotowire_slug": "tristan-enaruna-6333",
    "rotowire_id": "6333"
  },
  "4433184": {
    "espn_name": "Deivon Smith",
    "rotowire_slug": "deivon-smith-6732",
    "rotowire_id": "6732"
  },
  "5091677": {
    "espn_name": "Mojave King",
    "rotowire_slug": "mojave-king-5801",
    "rotowire_id": "5801"
  },
  "4432932": {
    "espn_name": "Max Abmas",
    "rotowire_slug": "max-abmas-6341",
    "rotowire_id": "6341"
  },
  "4897471": {
    "espn_name": "Saint Thomas",
    "rotowire_slug": "saint-thomas-6694",
    "rotowire_id": "6694"
  },
  "4590360": {
    "espn_name": "Chucky Hepburn",
    "rotowire_slug": "chucky-hepburn-6601",
    "rotowire_id": "6601"
  },
  "3936277": {
    "espn_name": "Trhae Mitchell",
    "rotowire_slug": "trhae-mitchell-5328",
    "rotowire_id": "5328"
  },
  "4432105": {
    "espn_name": "Tyrese Samuel",
    "rotowire_slug": "tyrese-samuel-6337",
    "rotowire_id": "6337"
  },
  "4277846": {
    "espn_name": "Alex O'Connell",
    "rotowire_slug": "alex-oconnell-5665",
    "rotowire_id": "5665"
  },
  "4702442": {
    "espn_name": "Matthew Murrell",
    "rotowire_slug": "matthew-murrell-6643",
    "rotowire_id": "6643"
  },
  "3136474": {
    "espn_name": "Khadeen Carrington",
    "rotowire_slug": "khadeen-carrington-4602",
    "rotowire_id": "4602"
  },
  "4683681": {
    "espn_name": "Fanbo Zeng",
    "rotowire_slug": "fanbo-zeng-5365",
    "rotowire_id": "5365"
  },
  "4592843": {
    "espn_name": "Brice Williams",
    "rotowire_slug": "brice-williams-6583",
    "rotowire_id": "6583"
  },
  "4702134": {
    "espn_name": "Norchad Omier",
    "rotowire_slug": "norchad-omier-6658",
    "rotowire_id": "6658"
  },
  "4683742": {
    "espn_name": "Julian Reese",
    "rotowire_slug": "julian-reese-6653",
    "rotowire_id": "6653"
  },
  "4433149": {
    "espn_name": "L.J. Cryer",
    "rotowire_slug": "lj-cryer-6644",
    "rotowire_id": "6644"
  }
}